{"jsonrpc":"2.0","id":1,"result":{"content":[{"type":"text","text":"{\n  \"file_path\": \"/windows/Program Files (x86)/Steam/steamui/localization/shared_brazilian-json.js\",\n  \"metadata\": {\n    \"file_path\": \"/windows/Program Files (x86)/Steam/steamui/localization/shared_brazilian-json.js\",\n    \"file_name\": \"shared_brazilian-json.js\",\n    \"file_size\": 241236,\n    \"created\": \"2022-09-20T01:28:47.370409300Z\",\n    \"modified\": \"2025-01-29T23:27:28Z\",\n    \"accessed\": \"2025-05-30T11:23:19.022365600Z\",\n    \"permissions\": \"755\",\n    \"is_executable\": true,\n    \"mime_type\": \"application/octet-stream\",\n    \"hashes\": {\n      \"md5\": \"7a911592a6e5b62a0a0d71e18f86295f\",\n      \"sha256\": \"2e9fa3cc14c428e818fad543eb4fc805eea53db81affa7d1dc2f784f448f685f\",\n      \"sha512\": \"f64ad50ba34725271112728941613f512d4d57edada8a6798d6c53446a6f61c950a63510ee4e8cfc52f051cb73f7bbb7c85ccde3e25421f41f378e20b8144196\",\n      \"blake3\": \"8b29bccabf7fd3a121bc8a8eafc640c8f923376a7ba528478eea17e362769d22\"\n    },\n    \"binary_info\": null,\n    \"extracted_strings\": null,\n    \"signature_info\": null,\n    \"hex_dump\": null,\n    \"owner_uid\": 1000,\n    \"group_gid\": 1000\n  },\n  \"hashes\": {\n    \"md5\": \"7a911592a6e5b62a0a0d71e18f86295f\",\n    \"sha256\": \"2e9fa3cc14c428e818fad543eb4fc805eea53db81affa7d1dc2f784f448f685f\",\n    \"sha512\": \"f64ad50ba34725271112728941613f512d4d57edada8a6798d6c53446a6f61c950a63510ee4e8cfc52f051cb73f7bbb7c85ccde3e25421f41f378e20b8144196\",\n    \"blake3\": \"8b29bccabf7fd3a121bc8a8eafc640c8f923376a7ba528478eea17e362769d22\"\n  },\n  \"strings\": [\n    \"\\\"use strict\\\";(self.webpackChunksteamui=self.webpackChunksteamui||[]).push([[3594],{72696:e=>{e.exports=JSON.parse('{\\\"language\\\":\\\"brazilian\\\",\\\"Steam_Platform\\\":\\\"Steam\\\",\\\"Button_About\\\":\\\"Sobre\\\",\\\"Button_Append\\\":\\\"Anexar\\\",\\\"Button_Back\\\":\\\"Voltar\\\",\\\"Button_Cancel\\\":\\\"Cancelar\\\",\\\"Button_Close\\\":\\\"Fechar\\\",\\\"Button_Clone\\\":\\\"Clonar\\\",\\\"Button_Confirm\\\":\\\"Confirmar\\\",\\\"Button_Copy\\\":\\\"Copiar\\\",\\\"Button_Copied\\\":\\\"Copiado\\\",\\\"Button_CopyClipboard\\\":\\\"Copiar p/ \",\n    \"rea de transfer\",\n    \"ncia\\\",\\\"Button_CopyLink\\\":\\\"Copiar link\\\",\\\"Button_Continue\\\":\\\"Continuar\\\",\\\"Button_Create\\\":\\\"Criar\\\",\\\"Button_Delete\\\":\\\"Excluir\\\",\\\"Button_Discuss\\\":\\\"Discuss\",\n    \"o\\\",\\\"Button_Dismiss\\\":\\\"Descartar\\\",\\\"Button_Edit\\\":\\\"Editar\\\",\\\"Button_Learn\\\":\\\"Saiba mais aqui\\\",\\\"Button_Publish\\\":\\\"Publicar\\\",\\\"Button_Published\\\":\\\"Publicado\\\",\\\"Button_Post\\\":\\\"Publicar\\\",\\\"Button_OK\\\":\\\"OK\\\",\\\"Button_Done\\\":\\\"OK\\\",\\\"Button_Overwrite\\\":\\\"Substituir\\\",\\\"Button_Retry\\\":\\\"Tentar novamente\\\",\\\"Button_Remove\\\":\\\"Remover\\\",\\\"Button_Revert\\\":\\\"Reverter\\\",\\\"Button_Save\\\":\\\"Salvar\\\",\\\"Button_Saved\\\":\\\"Salvo\\\",\\\"Button_Share\\\":\\\"Compartilhar\\\",\\\"Button_Update\\\":\\\"Atualizar\\\",\\\"Button_SaveAndContinue\\\":\\\"Salvar e continuar\\\",\\\"Button_SaveAndClose\\\":\\\"Salvar e fechar\\\",\\\"Button_Submit\\\":\\\"Enviar\\\",\\\"Button_Follow\\\":\\\"Seguir\\\",\\\"Button_Followed\\\":\\\"Seguindo\\\",\\\"Button_Ignore\\\":\\\"Ignorar\\\",\\\"Button_Ignored\\\":\\\"Ignorado\\\",\\\"Button_NotifyMe\\\":\\\"Ativar notifica\",\n    \"es\\\",\\\"Button_NotInterested\\\":\\\"Dispensar\\\",\\\"Button_Preview\\\":\\\"Pr\",\n    \"-visualizar\\\",\\\"Button_RateUp\\\":\\\"Gostei\\\",\\\"Button_ViewPage\\\":\\\"Acessar p\",\n    \"gina\\\",\\\"Button_Accept\\\":\\\"Aceitar\\\",\\\"Button_Reject\\\":\\\"Recusar\\\",\\\"Button_Go\\\":\\\"Ir\\\",\\\"Button_Got_It\\\":\\\"OK\\\",\\\"Button_Hide\\\":\\\"Ocultar\\\",\\\"Button_Load\\\":\\\"Carregar\\\",\\\"Button_Upload\\\":\\\"Enviar\\\",\\\"Button_Manage\\\":\\\"Gerenciar\\\",\\\"Button_DeleteAll\\\":\\\"Excluir tudo\\\",\\\"Button_TryAgain\\\":\\\"Tentar novamente\\\",\\\"Button_View\\\":\\\"Exibir\\\",\\\"Button_Next\\\":\\\"Avan\",\n    \"ar\\\",\\\"Button_Color\\\":\\\"Seletor de cor\\\",\\\"Button_Clear\\\":\\\"Limpar\\\",\\\"Flag_New\\\":\\\"Novidade\\\",\\\"StoreLink_Label\\\":\\\"Loja\\\",\\\"CommunityLink_Label\\\":\\\"Comunidade\\\",\\\"SupportLink_Label\\\":\\\"Suporte\\\",\\\"Error_Generic\\\":\\\"Erro\\\",\\\"Error_Generic_Label\\\":\\\"Erro:\\\",\\\"Error_ErrorCommunicatingWithNetwork\\\":\\\"Houve um erro na comunica\",\n    \"o com a rede. Tente novamente mais tarde.\\\",\\\"Dialog_DontShowMeAgain\\\":\\\"N\",\n    \"o exibir esta mensagem novamente\\\",\\\"Dialog_AreYouSure\\\":\\\"Tem certeza?\\\",\\\"ToolTip_CopyLinkToClipboard\\\":\\\"Copiar link para a \",\n    \"rea de transfer\",\n    \"ncia\\\",\\\"EventDisplay_Share_CopiedToClipboard\\\":\\\"Link copiado\\\",\\\"EventDisplay_Share_FailedToCopyToClipboard\\\":\\\"Falha ao copiar para a \",\n    \"rea de transfer\",\n    \"ncia\\\",\\\"Input_Error_NumberTooSmall\\\":\\\"N\",\n    \"mero pequeno demais.\\\",\\\"Input_Error_NumberTooLarge\\\":\\\"N\",\n    \"mero grande demais.\\\",\\\"Input_Error_MustBeURL\\\":\\\"O campo n\",\n    \"o inclui um URL v\",\n    \"lido.\\\",\\\"Input_Error_MustBeEmail\\\":\\\"O campo n\",\n    \"o inclui um e-mail v\",\n    \"lido.\\\",\\\"Input_Error_MustBeNumber\\\":\\\"O campo deve conter um n\",\n    \"mero.\\\",\\\"Input_Error_TooManyCharacters\\\":\\\"O campo ultrapassa o limite de caracteres (%1$s).\\\",\\\"Loading\\\":\\\"Carregando...\\\",\\\"Updating\\\":\\\"Atualizando...\\\",\\\"Uploading\\\":\\\"Enviando...\\\",\\\"Saving\\\":\\\"Salvando...\\\",\\\"Sending\\\":\\\"Enviando...\\\",\\\"Deleting\\\":\\\"Excluindo...\\\",\\\"Publishing\\\":\\\"Publicando...\\\",\\\"Uploading_Item\\\":\\\"Enviando: %1$s\\\",\\\"Settings\\\":\\\"Configura\",\n    \"es\\\",\\\"ViewDocumentation\\\":\\\"Ver documenta\",\n    \"o\\\",\\\"FriendSettings_AlwaysNewChatWindow\\\":\\\"Abrir novas conversas em janelas em vez de abas\\\",\\\"g_DisabledOnWeb\\\":\\\"Indispon\",\n    \"vel na vers\",\n    \"o web\\\",\\\"VoiceTransmissionType_Disabled\\\":\\\"Vers\",\n    \"o web s\",\n    \" compat\",\n    \"vel com microfone aberto\\\",\\\"VoiceVolume\\\":\\\"Volume\\\",\\\"VoiceSetupHeader\\\":\\\"Configura\",\n    \"o e teste de voz\\\",\\\"VoiceStartLocalMicTest\\\":\\\"Iniciar teste de microfone\\\",\\\"VoiceStopLocalMicTest\\\":\\\"Finalizar teste de microfone\\\",\\\"VoiceWhenMicIsWorking\\\":\\\"Caso o seu microfone esteja funcionando, a barra colorida pr\",\n    \"xima ao seu avatar se mover\",\n    \" quando voc\",\n    \" falar.\\\",\\\"VoiceDevice\\\":\\\"Dispositivo de entrada de voz\\\",\\\"VoiceOutputDevice\\\":\\\"Dispositivo de reprodu\",\n    \"o de voz\\\",\\\"VoiceInputGain\\\":\\\"Volume/Ganho de entrada\\\",\\\"VoiceInputGainExplainer\\\":\\\"(Meu microfone)\\\",\\\"VoiceOutputGain\\\":\\\"Volume/Ganho de sa\",\n    \"da\\\",\\\"VoiceOutputGainExplainer\\\":\\\"(Meus amigos)\\\",\\\"VoiceTransmissionType\\\":\\\"Pressionar para falar\\\",\\\"VoiceTransmissionType_Label\\\":\\\"Tipo de transmiss\",\n    \"o por voz\\\",\\\"VoiceTransmissionType_OpenMic\\\":\\\"Microfone aberto\\\",\\\"VoiceTransmissionType_PushToTalk\\\":\\\"Pressionar para falar\\\",\\\"VoiceTransmissionType_PushToMute\\\":\\\"Pressionar para silenciar\\\",\\\"VoiceClearHotKeyTooltip\\\":\\\"Remover atalho\\\",\\\"VoiceTransmissionTypeExplainer\\\":\\\"Pressione uma tecla ou bot\",\n    \"o definido por voc\",\n    \" para falar em canais de voz\\\",\\\"VoiceTransmissionType_WhenSpeaking\\\":\\\"Autom\",\n    \"tico\\\",\\\"VoiceTransmissionType_PushToTalk_Key\\\":\\\"Pressionar para falar: %1$s\\\",\\\"VoicePushToTalkPressHotKey\\\":\\\"Pressione uma tecla ou bot\",\n    \"o para atribuir\\\",\\\"VoicePushToTalkAssigned\\\":\\\"Tecla/Bot\",\n    \"o para pressionar para falar\\\",\\\"VoicePushToMuteAssigned\\\":\\\"Tecla/Bot\",\n    \"o para pressionar para silenciar\\\",\\\"VoiceMuteToggleAssigned\\\":\\\"Atalho para ativar/desativar o microfone\\\",\\\"VoicePushToSomethingSoundOption\\\":\\\"Reproduzir som ao ativar/desativar o microfone\\\",\\\"VoiceTransmisionThreshold\\\":\\\"Limiar para transmiss\",\n    \"o de voz\\\",\\\"VoiceTransmissionThresholdExplainer\\\":\\\"Quando o seu microfone estiver ligado, ru\",\n    \"do abaixo desse limite n\",\n    \"o ser\",\n    \" transmitido:\\\",\\\"VoiceTransmissionThresholdOff\\\":\\\"Desligado\\\",\\\"VoiceTransmissionThresholdMedium\\\":\\\"M\",\n    \"dio\\\",\\\"VoiceTransmissionThresholdHigh\\\":\\\"Alto\\\",\\\"VoiceTransmissionThresholdRecommended\\\":\\\"(recomendado)\\\",\\\"VoiceAdvancedSettings\\\":\\\"Configura\",\n    \"es avan\",\n    \"adas\\\",\\\"VoiceShowAdvancedSettings\\\":\\\"Exibir configura\",\n    \"es avan\",\n    \"adas\\\",\\\"VoiceHideAdvancedSettings\\\":\\\"Ocultar configura\",\n    \"es avan\",\n    \"adas\\\",\\\"VoiceAdvancedSettingsExplainer\\\":\\\"(Estas configura\",\n    \"es de microfone s\",\n    \"o gerenciadas pela sua plataforma ou navegador.)\\\",\\\"VoiceEchoCancellation\\\":\\\"Cancelamento de eco\\\",\\\"VoiceNoiseCancellation\\\":\\\"Cancelamento de ru\",\n    \"do\\\",\\\"VoiceAutoGainControl\\\":\\\"Controle autom\",\n    \"tico de volume/ganho\\\",\\\"DefaultMic\\\":\\\"Padr\",\n    \"o\\\",\\\"MicLoading...\\\":\\\"Carregando...\\\",\\\"DefaultOutputDevice\\\":\\\"Padr\",\n    \"o\\\",\\\"OutputDeviceLoading...\\\":\\\"Carregando...\\\",\\\"BreadCrumbs_AllEvents\\\":\\\"Todos os eventos\\\",\\\"BreadCrumbs_GameEvents\\\":\\\"Eventos de %1$s\\\",\\\"CreatorHome_ThisGame\\\":\\\"Sobre este jogo:\\\",\\\"CreatorHome_DevelopedBy\\\":\\\"Desenvolvido por:\\\",\\\"CreatorHome_PublishedBy\\\":\\\"Distribu\",\n    \"do por:\\\",\\\"CreatorHome_InFranchise\\\":\\\"Na s\",\n    \"rie:\\\",\\\"CreatorHome_Followers\\\":\\\"%1$s<br>seguidores\\\",\\\"CreatorHome_JustFollowers\\\":\\\"seguidores\\\",\\\"CreatorHome_Follow_tooltip\\\":\\\"Siga este criador para ser notificado por e-mail e na Loja Steam sobre futuros lan\",\n    \"amentos. \",\n    \" poss\",\n    \"vel desativar as notifica\",\n    \"es por e-mail quando quiser.\\\",\\\"EventBrowse_MoreEventsTitle\\\":\\\"Mais eventos de %1$s\\\",\\\"EventBrowse_MoreEventsBtn\\\":\\\"Ver tudo\\\",\\\"EventBrowse_AllEventsBtn\\\":\\\"Ver todos os eventos\\\",\\\"EventBrowse_ViewLatestUpdate\\\":\\\"Ver\\\",\\\"EventBrowse_LatestUpdateTime_Button\\\":\\\"Ver todas as atualiza\",\n    \"es (\",\n    \"ltima: %1$s)\\\",\\\"EventBrowse_RecentUpdates\\\":\\\"Atualiza\",\n    \"es recentes\\\",\\\"EventBrowse_RecentEvents\\\":\\\"Eventos e an\",\n    \"ncios recentes\\\",\\\"EventBrowse_LastUpdateDate\\\":\\\"\",\n    \"ltima atualiza\",\n    \"o: %1$s\\\",\\\"EventCurator_BrowseDialog_Title\\\":\\\"Not\",\n    \"cias de Curadores Steam\\\",\\\"EventCurator_BrowseDialog_Desc\\\":\\\"Siga os seus Curadores Steam favoritos para acompanhar as not\",\n    \"cias diretamente da central de not\",\n    \"cias!\\\",\\\"EventCurator_BrowseDialog_LangCurator\\\":\\\"Curadores Steam em %1$s\\\",\\\"EventCurator_NoEventsFound_Title\\\":\\\"Nenhuma publica\",\n    \"o encontrada\\\",\\\"EventCurator_NoEventsFound_Body\\\":\\\"Nenhuma publica\",\n    \"o deste curador foi encontrada\\\",\\\"EventCurator_BrowseMore\\\":\\\"Descubra mais fontes\\\",\\\"EventCurator_FeedCaption_Long\\\":\\\"Siga alguns desses Curadores Steam para acompanhar as not\",\n    \"cias diretamente da central de not\",\n    \"cias!\\\",\\\"EventCurator_DismissTitle\\\":\\\"Ocultar sugest\",\n    \"es de not\",\n    \"cias\\\",\\\"EventCurator_DismissBody\\\":\\\"Esta op\",\n    \"o ocultar\",\n    \" sugest\",\n    \"es de not\",\n    \"cias neste dispositivo. Para ver as not\",\n    \"cias, acesse a aba de Curadores Steam na central de not\",\n    \"cias\\\",\\\"EventCalendar_Title\\\":\\\"Central de not\",\n    \"cias%1$sdo Steam\\\",\\\"EventCalendar_TabTitle_Global\\\":\\\"Central de not\",\n    \"cias do Steam\\\",\\\"EventCalendar_TabTitle_GroupHub\\\":\\\"Central de not\",\n    \"cias do Steam \",\n    \" %1$s\\\",\\\"EventCalendar_TabTitle_GroupNameAndEventDetail\\\":\\\"%1$s \",\n    \" %2$s \",\n    \" Central de not\",\n    \"cias\\\",\\\"EventCalendar_FilterSubSection_EventTypeGroups\\\":\\\"Exibir estes tipos de publica\",\n    \"es\\\",\\\"EventCalendar_FilterSubSection_GameSources\\\":\\\"Exibir publica\",\n    \"es destas fontes\\\",\\\"EventCalendar_FilterSubSection_CuratorSources\\\":\\\"Exibir publica\",\n    \"es de curadores\\\",\\\"EventCalendar_FilterSubSection_CollectionSources\\\":\\\"Exibir publica\",\n    \"es destas fontes\\\",\\\"EventCalendar_BrowseCurators\\\":\\\"Explorar curadores\\\",\\\"EventCalendar_EmptyCalendar\\\":\\\"Nada encontrado. Tente usar outros crit\",\n    \"rios de busca na barra lateral.\\\",\\\"EventCalendar_DisabledFilter_LoginPrompt\\\":\\\"Inicie a sess\",\n    \"o para usar estas categorias\\\",\\\"EventCalendar_MainLoginPrompt\\\":\\\"Inicie a sess\",\n    \"o para ver a sua central de not\",\n    \"cias\\\",\\\"EventCalendar_NoFutureEvents\\\":\\\"Nenhum evento futuro encontrado\\\",\\\"EventCalendar_NoPastEvents\\\":\\\"Nenhuma publica\",\n    \"o antiga encontrada\\\",\\\"EventCalendar_NoMoreFutureEvents\\\":\\\"Nenhum evento futuro encontrado\\\",\\\"EventCalendar_NoMorePastEvents\\\":\\\"Nenhuma publica\",\n    \"o antiga encontrada\\\",\\\"EventCalendar_UpdatesViewHeader\\\":\\\"Atualiza\",\n    \"es recentes\\\",\\\"EventCalendar_NoPastUpdates\\\":\\\"Nenhuma atualiza\",\n    \"o encontrada\\\",\\\"EventCalendar_NoMorePastUpdates\\\":\\\"Nenhuma outra atualiza\",\n    \"o encontrada\\\",\\\"EventCalendar_ResetFiltersButton\\\":\\\"Ver todas as publica\",\n    \"es\\\",\\\"EventCalendar_ResetFilters_ttip\\\":\\\"Restaura a configura\",\n    \"o original dos filtros\\\",\\\"EventCalendar_GameSearch\\\":\\\"Buscar jogos\\\",\\\"EventCalendar_UniversalSearch\\\":\\\"Buscar\\\",\\\"EventCalendar_GameSearch_NoneFound\\\":\\\"Nenhum encontrado\\\",\\\"EventCalendar_SearchResultsHeader_GameSection\\\":\\\"Jogos\\\",\\\"EventCalendar_SearchResultsHeader_GameAndDLCSection\\\":\\\"Jogos e conte\",\n    \"dos adicionais\\\",\\\"EventCalendar_SearchResultsHeader_CuratorSection\\\":\\\"Curadores\\\",\\\"EventCalendar_FollowingCurator\\\":\\\"seguindo\\\",\\\"EventCalendar_GroupTitle_Curators\\\":\\\"De curadores que voc\",\n    \" segue\\\",\\\"EventCalendar_GroupTitle_FeaturedCurators\\\":\\\"Not\",\n    \"cias de curadores em destaque\\\",\\\"EventCalendar_NewsLanguage_Title\\\":\\\"Exibindo fontes de not\",\n    \"cias dispon\",\n    \"veis nos seus idiomas\\\",\\\"EventCalendar_NewsLanguage_Text\\\":\\\"Atualize as suas %1$s para ver conte\",\n    \"dos e fontes em mais idiomas\\\",\\\"EventCalendar_NewsLanguage_TextInHyperlink\\\":\\\"prefer\",\n    \"ncias de idioma da loja\\\",\\\"EventCalendar_TimeEventLastPlayed\\\":\\\"\",\n    \"ltima sess\",\n    \"o %1$s\\\",\\\"EventCalendar_TimeEventWishlisted\\\":\\\"Adic. \",\n    \" lista de desejos %1$s\\\",\\\"EventCalendar_GlobalCalendar_Action\\\":\\\"Voltar \",\n    \" central de not\",\n    \"cias\\\",\\\"EventCalendar_SpecificCalendar\\\":\\\"Central de not\",\n    \"cias de%2$s%1$s\\\",\\\"EventCalendar_Goto_SpecificCalendar\\\":\\\"Ir para a central de not\",\n    \"cias de %1$s\\\",\\\"EventCalendar_Goto_RSSFeed\\\":\\\"Abrir feed RSS de %1$s\\\",\\\"EventCalendar_SingleAppIsMuted\\\":\\\"Aviso: este jogo est\",\n    \" silenciado e n\",\n    \"o ser\",\n    \" exibido na sua central de not\",\n    \"cias personalizada.\\\",\\\"EventCalendar_SingleGroupIsMuted\\\":\\\"Aviso: este grupo est\",\n    \" silenciado e n\",\n    \"o ser\",\n    \" exibido na sua central de not\",\n    \"cias personalizada.\\\",\\\"EventCalendar_WatchYouTubeVideo\\\":\\\"Ver v\",\n    \"deo do YouTube\\\",\\\"EventCalendar_WatchLiveBroadcast\\\":\\\"Ver transmiss\",\n    \"o ao vivo\\\",\\\"EventModTile_Moderator\\\":\\\"Moderador(a): %1$s\\\",\\\"EventModTile_EventCreator\\\":\\\"Originalmente criado por: %1$s\\\",\\\"EventModTile_EventLastUpdator\\\":\\\"\",\n    \"ltima atualiza\",\n    \"o por: %1$s\\\",\\\"EventModTile_Signer\\\":\\\"Autoridade: %1$s\\\",\\\"EventModTile_Action_Reviewed\\\":\\\"%2$s (%1$s) marcou como analisado\\\",\\\"EventModTile_Action_ReReviewed\\\":\\\"%2$s (%1$s) marcou como reanalisado\\\",\\\"EventModTile_Action_UnReviewed\\\":\\\"%2$s (%1$s) desmarcou como analisado\\\",\\\"EventModTile_Action_NewEventType\\\":\\\"%2$s (%1$s) mudou para a categoria %3$s\\\",\\\"EventModTile_Action_SeasonTagUpdate\\\":\\\"%2$s (%1$s) atualizou o marcador sazonal %3$s\\\",\\\"EventModTile_Action_RemoveFromSC\\\":\\\"%2$s (%1$s) ocultou o evento do Steam China\\\",\\\"EventModTile_Action_FlagAdultContent\\\":\\\"%2$s (%1$s) sinalizou como conte\",\n    \"do adulto\\\",\\\"EventModTile_Action_RemoveAdultContent\\\":\\\"%2$s (%1$s) removeu sinaliza\",\n    \"o de conte\",\n    \"do adulto\\\",\\\"EventModTile_Action_Title\\\":\\\"Hist\",\n    \"rico de modera\",\n    \"o\\\",\\\"EventModTile_Action_More\\\":\\\"Exibir %1$s a\",\n    \"o(s) mais antiga(s)\\\",\\\"EventModTile_Action_Hide\\\":\\\"Ocultar a\",\n    \"o(s)\\\",\\\"SteamLabs\\\":\\\"Laborat\",\n    \"rio Steam\\\",\\\"SteamLabs_ExperimentNumber\\\":\\\"Experimento %1$s\\\",\\\"SteamLabs_DiscussionLink\\\":\\\"Discutir experimento\\\",\\\"SteamLabs_OptOutLink\\\":\\\"Sair do experimento\\\",\\\"EventCalendar_SignIn_Title\\\":\\\"Inicie a sess\",\n    \"o para obter not\",\n    \"cias personalizadas\\\",\\\"EventCalendar_SignIn_Text\\\":\\\"Inicie a sess\",\n    \"o com a sua conta Steam para acessar a sua central personalizada ou explore not\",\n    \"cias e atualiza\",\n    \"es em destaque abaixo.\\\",\\\"EventCalendar_FutureEventsHint\\\":\\\"Role para cima para ver o que vem por a\",\n    \"\\\",\\\"EventCalendar_FutureEventsLink\\\":\\\"Ver todos os eventos futuros\\\",\\\"EventCalendar_LoadEventsProgress\\\":\\\"%1$s eventos carregados (%2$s)\\\",\\\"EventCalendar_LoadEventsFilters\\\":\\\"Voc\",\n    \" pode ajustar as suas op\",\n    \"es e os seus filtros para ver mais eventos nesta p\",\n    \"gina\\\",\\\"EventCalendar_FutureEventsHeader\\\":\\\"Em breve\\\",\\\"EventCalendar_PastEventsLink\\\":\\\"Ver publica\",\n    \"es anteriores\\\",\\\"EventCalendar_LiveAndRecentEventsHeader\\\":\\\"Acontecendo agora e recentes\\\",\\\"EventCalendar_TuneIn\\\":\\\"Assista\\\",\\\"EventCalendar_LiveNow\\\":\\\"No ar\\\",\\\"EventCalendar_TimeLeft\\\":\\\"Termina em %1$s\\\",\\\"EventCalendar_PostedAtTime\\\":\\\"Publicado: %1$s\\\",\\\"EventCalendar_StartedAtTime\\\":\\\"In\",\n    \"cio: %1$s\\\",\\\"EventCalendar_Upcoming\\\":\\\"em breve\\\",\\\"EventCalendar_WillStartAtTime\\\":\\\"Come\",\n    \"a: %1$s\\\",\\\"EventCalendar_WillStartAfterDuration\\\":\\\"Come\",\n    \"a em %1$s\\\",\\\"EventCalendar_WillStartAtDateTime\\\":\\\"%1$s \",\n    \" %2$s\\\",\\\"EventCalendar_LaterToday\\\":\\\"ainda hoje\\\",\\\"EventCalendar_Tomorrow\\\":\\\"amanh\",\n    \"\\\",\\\"EventCalendar_NextWeek\\\":\\\"semana que vem\\\",\\\"EventCalendar_LaterThisMonth\\\":\\\"este m\",\n    \"s\\\",\\\"EventCalendar_MuchLater\\\":\\\"no futuro\\\",\\\"EventCalendar_MuteApp\\\":\\\"Silenciar aplicativo\\\",\\\"EventCalendar_MuteApp_Title\\\":\\\"Silenciar %1$s\\\",\\\"EventCalendar_Ignore\\\":\\\"Ignorar\\\",\\\"EventCalendar_IgnoreApp\\\":\\\"Ignorar %1$s\\\",\\\"EventCalendar_IgnoreApp_ttip\\\":\\\"T\",\n    \"tulos ignorados n\",\n    \"o ser\",\n    \"o recomendados para voc\",\n    \", nem aparecer\",\n    \"o em \",\n    \"reas de destaque.\\\",\\\"EventCalendar_IgnoreApp_newhub\\\":\\\"A central de not\",\n    \"cias n\",\n    \"o exibir\",\n    \" eventos e an\",\n    \"ncios de jogos que voc\",\n    \" tenha ignorado na Loja Steam. Gerencie os seus jogos ignorados aqui:\\\",\\\"EventCalendar_FollowCurator\\\":\\\"Seguir Curador Steam: %1$s\\\",\\\"EventCalendar_FollowCurator_ttip\\\":\\\"Ao seguir este curador, os artigos dele ser\",\n    \"o exibidos na sua central de not\",\n    \"cias e as recomenda\",\n    \"es, na Loja Steam.\\\",\\\"EventCalendar_UnFollowCurator\\\":\\\"Deixar de seguir Curador Steam: %1$s\\\",\\\"EventCalendar_UnFollowCurator_ttip\\\":\\\"Voc\",\n    \" est\",\n    \" seguindo este curador. Ao deixar de seguir, os artigos dele deixar\",\n    \"o de ser exibidos na sua central de not\",\n    \"cias, o que tamb\",\n    \"m acontecer\",\n    \" com as recomenda\",\n    \"es na Loja Steam.\\\",\\\"EventCalendar_UnignoreApp\\\":\\\"Deixar de ignorar %1$s\\\",\\\"EventCalendar_UnMuteApp_Title\\\":\\\"Voltar a exibir %1$s\\\",\\\"EventCalendar_MuteApp_ttip\\\":\\\"Remove este jogo da sua central de not\",\n    \"cias e bloqueia comunicados futuros.\\\",\\\"EventCalendar_UnMuteApp_ttip\\\":\\\"Voltar a exibir o jogo na sua central de not\",\n    \"cias e desbloquear comunicados futuros.\\\",\\\"EventCalendar_MuteApp_details\\\":\\\"Impedir que este conte\",\n    \"do apare\",\n    \"a na sua central de not\",\n    \"cias e bloquear todos os comunicados futuros. Decis\",\n    \"es de silenciamento s\",\n    \"o revers\",\n    \"veis, basta acessar esta p\",\n    \"gina: \\\",\\\"EventCalendar_ManageMutedApps\\\":\\\"Gerenciar aplicativos silenciados\\\",\\\"EventCalendar_ManageMutedSources\\\":\\\"Gerenciar fontes silenciadas\\\",\\\"EventCalendar_ManageStorePref\\\":\\\"Gerenciar prefer\",\n    \"ncias da loja\\\",\\\"EventCalendar_MuteApp_Unknown\\\":\\\"Desconhecido\\\",\\\"EVentCalendar_Hide_EventType\\\":\\\"Ocultar publica\",\n    \"es do tipo \\\\\\\\\\\"%1$s\\\\\\\\\\\"\\\",\\\"EventCalender_LastPlayed\\\":\\\"\",\n    \"ltima sess\",\n    \"o: %1$s\\\",\\\"EventCalender_Reason_recent\\\":\\\"Jogo rec\",\n    \"m-jogado\\\",\\\"EventCalender_Reason_library\\\":\\\"Jogo presente na sua biblioteca\\\",\\\"EventCalender_Reason_following\\\":\\\"Jogo seguido por voc\",\n    \"\\\",\\\"EventCalender_Reason_wishlist\\\":\\\"Jogo presente na sua lista de desejos\\\",\\\"EventCalender_Reason_recommended\\\":\\\"Jogo recomendado para voc\",\n    \"\\\",\\\"EventCalender_Reason_steam\\\":\\\"Publica\",\n    \"o do Steam\\\",\\\"EventCalender_Reason_topx\\\":\\\"Jogo entre os mais vendidos\\\",\\\"EventCalender_Reason_featured\\\":\\\"Publica\",\n    \"o em destaque\\\",\\\"EventCalender_Reason_curator\\\":\\\"Curador seguido por voc\",\n    \"\\\",\\\"EventCalender_Hide_Reason_recent\\\":\\\"Ocultar publica\",\n    \"es de jogos rec\",\n    \"m-jogados\\\",\\\"EventCalender_Hide_Reason_library\\\":\\\"Ocultar publica\",\n    \"es sobre jogos na sua biblioteca\\\",\\\"EventCalender_Hide_Reason_following\\\":\\\"Ocultar publica\",\n    \"es sobre jogos que voc\",\n    \" segue\\\",\\\"EventCalender_Hide_Reason_wishlist\\\":\\\"Ocultar publica\",\n    \"es sobre jogos na sua lista de desejos\\\",\\\"EventCalender_Hide_Reason_recommended\\\":\\\"Ocultar publica\",\n    \"es sobre jogos recomendados para voc\",\n    \"\\\",\\\"EventCalender_Hide_Reason_steam\\\":\\\"Ocultar publica\",\n    \"es do Steam\\\",\\\"EventCalender_Hide_Reason_topx\\\":\\\"Ocultar publica\",\n    \"es de jogos mais vendidos\\\",\\\"EventCalender_Hide_Reason_featured\\\":\\\"Ocultar publica\",\n    \"es em destaque\\\",\\\"EventCalender_Hide_Reason_curator\\\":\\\"Ocultar publica\",\n    \"es de curadores\\\",\\\"EventCalendar_ForceDesktopView\\\":\\\"Ver vers\",\n    \"o para computadores\\\",\\\"EventCalendar_ShowResponsiveView\\\":\\\"Ver vers\",\n    \"o adapt\",\n    \"vel\\\",\\\"EventCalendar_EventTypeGroup_news\\\":\\\"Novidades\\\",\\\"EventCalendar_EventTypeGroup_ttip_news\\\":\\\"Inclui not\",\n    \"cias, blogs de desenvolvimento e an\",\n    \"ncios\\\",\\\"EventCalendar_EventTypeGroup_events\\\":\\\"Eventos\\\",\\\"EventCalendar_EventTypeGroup_ttip_events\\\":\\\"Inclui eventos no jogo, on-line, em salas de conversa e no mundo real\\\",\\\"EventCalendar_EventTypeGroup_streaming\\\":\\\"Transmiss\",\n    \"es ao vivo\\\",\\\"EventCalendar_EventTypeGroup_ttip_streaming\\\":\\\"Inclui transmiss\",\n    \"es ao vivo de desenvolvedores, como torneios e demonstra\",\n    \"es do jogo\\\",\\\"EventCalendar_EventTypeGroup_updates\\\":\\\"Atualiza\",\n    \"es de conte\",\n    \"do\\\",\\\"EventCalendar_EventTypeGroup_ttip_updates\\\":\\\"Inclui not\",\n    \"cias sobre novos conte\",\n    \"dos, expans\",\n    \"es, conte\",\n    \"dos adicionais e corre\",\n    \"es para jogos\\\",\\\"EventCalendar_EventTypeGroup_releases\\\":\\\"Lan\",\n    \"amentos\\\",\\\"EventCalendar_EventTypeGroup_ttip_releases\\\":\\\"Inclui datas de lan\",\n    \"amentos de jogos, betas, temporadas e conte\",\n    \"dos adicionais.\\\",\\\"EventCalendar_EventTypeGroup_sales\\\":\\\"Promo\",\n    \"es\\\",\\\"EventCalendar_EventTypeGroup_ttip_sales\\\":\\\"Inclui descontos, promo\",\n    \"es e testes gratuitos\\\",\\\"EventCalendar_GameSource_recent\\\":\\\"Rec\",\n    \"m-jogados\\\",\\\"EventCalendar_GameSource_ttip_recent\\\":\\\"Incluir publica\",\n    \"es sobre jogos que tenha jogado ou comprado nos \",\n    \"ltimos seis meses\\\",\\\"EventCalendar_GameSource_EventExplanation_ttip_recent\\\":\\\"Voc\",\n    \" jogou este jogo nos \",\n    \"ltimos seis meses\\\",\\\"EventCalendar_GameSource_library\\\":\\\"Biblioteca\\\",\\\"EventCalendar_GameSource_inLibrary\\\":\\\"Na biblioteca\\\",\\\"EventCalendar_GameSource_ttip_library\\\":\\\"Incluir publica\",\n    \"es sobre jogos na sua biblioteca\\\",\\\"EventCalendar_GameSource_EventExplanation_ttip_library\\\":\\\"Jogo presente na sua biblioteca\\\",\\\"EventCalendar_GameSource_wishlist\\\":\\\"Lista de desejos\\\",\\\"EventCalendar_GameSource_onWishlist\\\":\\\"Na lista de desejos\\\",\\\"EventCalendar_GameSource_ttip_wishlist\\\":\\\"Incluir publica\",\n    \"es sobre jogos na sua lista de desejos\\\",\\\"EventCalendar_GameSource_EventExplanation_ttip_wishlist\\\":\\\"Jogo presente na sua lista de desejos\\\",\\\"EventCalendar_GameSource_following\\\":\\\"Seguindo\\\",\\\"EventCalendar_GameSource_followed\\\":\\\"Seguindo\\\",\\\"EventCalendar_GameSource_ttip_following\\\":\\\"Incluir publica\",\n    \"es sobre jogos que voc\",\n    \" segue\\\",\\\"EventCalendar_GameSource_EventExplanation_ttip_following\\\":\\\"\",\n    \" um jogo que voc\",\n    \" segue\\\",\\\"EventCalendar_GameSource_recommended\\\":\\\"Recomendados\\\",\\\"EventCalendar_GameSource_recommended_Verbose\\\":\\\"Jogo recomendado\\\",\\\"EventCalendar_GameSource_ttip_recommended\\\":\\\"Incluir publica\",\n    \"es sobre jogos que achamos que voc\",\n    \" vai gostar\\\",\\\"EventCalendar_GameSource_EventExplanation_ttip_recommended\\\":\\\"\",\n    \" um jogo que achamos que vai gostar\\\",\\\"EventCalendar_GameSource_steam\\\":\\\"Steam\\\",\\\"EventCalendar_GameSource_ttip_steam\\\":\\\"Incluir publica\",\n    \"es sobre o Steam\\\",\\\"EventCalendar_GameSource_EventExplanation_ttip_steam\\\":\\\"Publica\",\n    \"o sobre o Steam\\\",\\\"EventCalendar_GameSource_topx\\\":\\\"Mais vendidos\\\",\\\"EventCalendar_GameSource_ttip_topx\\\":\\\"Incluir publica\",\n    \"es sobre jogos que estejam na lista de mais vendidos na regi\",\n    \"o\\\",\\\"EventCalendar_GameSource_featured\\\":\\\"Em destaque\\\",\\\"EventCalendar_GameSource_ttip_featured\\\":\\\"Incluir publica\",\n    \"es em destaque, como os de jogos mais vendidos\\\",\\\"EventCalendar_GameSource_curator\\\":\\\"Curadores que voc\",\n    \" segue\\\",\\\"EventCalendar_GameSource_ttip_curator\\\":\\\"Incluir publica\",\n    \"es de curadores que voc\",\n    \" segue no Steam\\\",\\\"EventCalendar_GameSource_UnhideCuratorsDialog_Title\\\":\\\"Exibir curadores?\\\",\\\"EventCalendar_GameSource_UnhideCuratorsDialog_Description\\\":\\\"Voc\",\n    \" come\",\n    \"ou a seguir um Curador Steam. Deseja incluir not\",\n    \"cias de curadores na sua central de not\",\n    \"cias?\\\",\\\"EventCalendar_GameSource_UnhideCuratorsDialog_OKButton\\\":\\\"Sim\\\",\\\"EventCalendar_GameSource_UnhideCuratorsDialog_CancelButton\\\":\\\"N\",\n    \"o\\\",\\\"EventCalendar_EditFilters\\\":\\\"Op\",\n    \"es e filtros\\\",\\\"EventCalendar_CloseFilters\\\":\\\"Central de not\",\n    \"cias\\\",\\\"EventCalendar_FiltersTitle\\\":\\\"Filtros\\\",\\\"EventCalendar_FiltersDescription\\\":\\\"Gerencie quais tipos e fontes de not\",\n    \"cias s\",\n    \"o exibidos na sua central de not\",\n    \"cias\\\",\\\"EventCalendar_FiltersDescription_NonPersonalized\\\":\\\"Gerencie quais tipos de eventos s\",\n    \"o exibidos nesta p\",\n    \"gina\\\",\\\"EventCalendar_NewsChannels\\\":\\\"Seus eventos e not\",\n    \"cias\\\",\\\"EventCalendar_NewsChannels_Global\\\":\\\"Not\",\n    \"cias e eventos globais\\\",\\\"EventCalendar_NewsChannels_Discover\\\":\\\"Descobrir\\\",\\\"EventCalendar_NewsChannel_YourNews\\\":\\\"Para voc\",\n    \"\\\",\\\"EventCalendar_NewsChannel_YourNews_HeaderTitle\\\":\\\"Not\",\n    \"cias de jogos para voc\",\n    \"\\\",\\\"EventCalendar_NewsChannel_Upcoming\\\":\\\"Seus eventos futuros\\\",\\\"EventCalendar_NewsChannel_UpcomingShort\\\":\\\"Em breve\\\",\\\"EventCalendar_NewsChannel_Featured\\\":\\\"Destaques\\\",\\\"EventCalendar_NewsChannel_Featured_HeaderTitle\\\":\\\"Not\",\n    \"cias em destaque\\\",\\\"EventCalendar_NewsChannel_Personalized\\\":\\\"Personalizado\\\",\\\"EventCalendar_NewsChannel_Filtered\\\":\\\"Filtrados\\\",\\\"EventCalendar_NewsChannel_AllGames\\\":\\\"De todos os jogos\\\",\\\"EventCalendar_NewsChannel_TopSellers\\\":\\\"Fontes mais populares\\\",\\\"EventCalendar_NewsChannel_Press\\\":\\\"Curadores\\\",\\\"EventCalendar_Collection_News_Title\\\":\\\"Descubra novos Curadores\\\",\\\"EventCalendar_Collection_News_Subtitle\\\":\\\"Explore os \",\n    \"ltimos artigos das melhores fontes de not\",\n    \"cia do mundo dos jogos. Siga um Curador Steam para adicionar as not\",\n    \"cias e recomenda\",\n    \"es de jogos dele \",\n    \" sua central de not\",\n    \"cias do Steam.\\\",\\\"EventCalendar_NewsChannel_Steam\\\":\\\"Steam\\\",\\\"EventCalendar_NewsChannel_SteamSubtitle\\\":\\\"Blog e not\",\n    \"cias do Steam\\\",\\\"EventCalendar_NewsChannel_Steam_HeaderTitle\\\":\\\"Not\",\n    \"cias oficiais do Steam\\\",\\\"EventCalendar_NewsChannel_All\\\":\\\"Todas as not\",\n    \"cias\\\",\\\"EventCalendar_NewsChannel_AllSales\\\":\\\"Todas as promo\",\n    \"es\\\",\\\"EventCalendar_NewsChannel_AssociatedPress\\\":\\\"Eventos de imprensa associados a aplicativos\\\",\\\"EventCalendar_NewsChannel_Halloween\\\":\\\"Eventos de Dia das Bruxas\\\",\\\"EventCalendar_NewsChannel_HalloweenSubtitle\\\":\\\"Cuidado: assustadores\\\",\\\"EventCalendar_Collection_Halloween_Title\\\":\\\"Eventos de Dia das Bruxas\\\",\\\"EventCalendar_Collection_Halloween_Subtitle\\\":\\\"Explore assustadores eventos e not\",\n    \"cias de Dia das Bruxas de jogos no Steam\\\",\\\"EventDisplay_Admin_Title\\\":\\\"Administra\",\n    \"o:\\\",\\\"EventDisplay_ViewInLibrary\\\":\\\"Ver na biblioteca\\\",\\\"EventDisplay_ViewStorePage\\\":\\\"Ver p\",\n    \"gina da loja\\\",\\\"EventDisplay_RSSFeed\\\":\\\"Feed RSS\\\",\\\"EventDisplay_RSSFeed_ExtraShort\\\":\\\"RSS\\\",\\\"EventDisplay_ViewCommunityPage\\\":\\\"Ver p\",\n    \"gina na comunidade\\\",\\\"EventDisplay_ViewForum\\\":\\\"Ver f\",\n    \"rum de discuss\",\n    \"es\\\",\\\"EventDisplay_ViewRssFeed\\\":\\\"Ver feed RSS\\\",\\\"EventDisplay_LinksDropDown_ExtraShort\\\":\\\"Links\\\",\\\"EventDisplay_ViewInLibrary_ExtraShort\\\":\\\"Biblioteca\\\",\\\"EventDisplay_ViewStorePage_ExtraShort\\\":\\\"Loja\\\",\\\"EventDisplay_ViewCommunityPage_ExtraShort\\\":\\\"Comunidade\\\",\\\"EventDisplay_ViewForum_ExtraShort\\\":\\\"F\",\n    \"rum\\\",\\\"EventDisplay_ViewRssFeed_ExtraShort\\\":\\\"RSS\\\",\\\"EventDisplay_Admin\\\":\\\"Painel administrativo\\\",\\\"EventDisplay_Admin_ExtraShort\\\":\\\"Administrador\\\",\\\"EventDisplay_OnWishlist\\\":\\\"Na sua lista de desejos\\\",\\\"EventDisplay_Follow\\\":\\\"Jogo que voc\",\n    \" segue\\\",\\\"EventDisplay_NewsHubSubtitle\\\":\\\"Central de not\",\n    \"cias\\\",\\\"EventDisplay_CallToAction_LearnMore\\\":\\\"Saiba mais\\\",\\\"EventDisplay_CallToAction_InLibrary\\\":\\\"Na biblioteca\\\",\\\"EventDisplay_CallToAction_PlayNow\\\":\\\"Jogar agora\\\",\\\"EventDisplay_CallToAction_ComingSoon\\\":\\\"Em breve\\\",\\\"EventDisplay_CallToAction_Prepurchase_Short\\\":\\\"Pr\",\n    \"-venda\\\",\\\"EventDisplay_CallToAction_ShowPurchaseOptions_Button\\\":\\\"Op\",\n    \"es de compra\\\",\\\"EventDisplay_CallToAction_FreeToPlay\\\":\\\"Gratuito para jogar\\\",\\\"EventDisplay_CallToAction_PlayNowForFree\\\":\\\"Jogue gratuitamente!\\\",\\\"EventDisplay_CallToAction_VisitStore\\\":\\\"Ver p\",\n    \"gina na loja\\\",\\\"EventDisplay_CallToAction_FreeDemo\\\":\\\"Demonstra\",\n    \"o gratuita\\\",\\\"EventDisplay_CallToAction_AddToAccount\\\":\\\"Adicionar \",\n    \" conta\\\",\\\"EventDisplay_CallToAction_Free\\\":\\\"Gratuito\\\",\\\"EventDisplay_Events\\\":\\\"Painel administrativo\\\",\\\"EventDisplay_SeeOldVersion\\\":\\\"Ver vers\",\n    \"o exibida a usu\",\n    \"rios\\\",\\\"EventDisplay_SalesPage\\\":\\\"Ver p\",\n    \"gina de promo\",\n    \"es da loja\\\",\\\"EventDisplay_StatsPage\\\":\\\"(Uso interno da Valve) P\",\n    \"gina de estat\",\n    \"sticas\\\",\\\"EventDisplay_InvitationPlannerPage\\\":\\\"(Uso interno da Valve) P\",\n    \"gina de planejamento de convites\\\",\\\"EventDisplay_PromotionEditor\\\":\\\"(Uso interno da Valve) Planejamento de promo\",\n    \"o\\\",\\\"EventDisplay_CategoryEditor\\\":\\\"(Uso interno da Valve) Editor de categoria de central de conte\",\n    \"do\\\",\\\"EventDisplay_ViewOnStore\\\":\\\"Ver na loja\\\",\\\"EventDisplay_ViewOnCommunity\\\":\\\"Ver na comunidade\\\",\\\"EventDisplay_PreviewOnCommunity\\\":\\\"Pr\",\n    \"-visualizar na comunidade\\\",\\\"EventDisplay_NoEventsToSee\\\":\\\"Nenhum evento encontrado\\\",\\\"EventDisplay_RightColumnTitle_Game\\\":\\\"Jogo\\\",\\\"EventDisplay_RightColumnTitle_Blog\\\":\\\"Blog\\\",\\\"EventDisplay_RightColumnTitle_DateAndTime\\\":\\\"Data e hora\\\",\\\"EventDisplay_RightColumnTitle_EventType\\\":\\\"Tipo\\\",\\\"EventDisplay_PostedBy\\\":\\\"por \\\",\\\"EventDisplay_Reminder_SetReminder\\\":\\\"Agendar lembrete\\\",\\\"EventDisplay_Reminder_GetNotification_Via\\\":\\\"Receber notifica\",\n    \"o\\\",\\\"EventDisplay_Reminder_ViaEmail\\\":\\\"por e-mail\\\",\\\"EventDisplay_Reminder_ViaMobileApp\\\":\\\"por aplicativo m\",\n    \"vel\\\",\\\"EventDisplay_Reminder_FollowEvent\\\":\\\"Seguir evento\\\",\\\"EventDisplay_Reminder_FollowEvent_ttip\\\":\\\"Siga o evento para ser notificado quando come\",\n    \"ar.\\\",\\\"EventDisplay_Reminder_RemindAtStart\\\":\\\"Quando o evento come\",\n    \"ar\\\",\\\"EventDisplay_Reminder_RemindAtStart_ttip\\\":\\\"Voc\",\n    \" ser\",\n    \" notificado no Steam quando o evento come\",\n    \"ar.\\\",\\\"EventDisplay_Reminder_IgnoreEvent\\\":\\\"Ignorar evento\\\",\\\"EventDisplay_Reminder_IgnoreStop\\\":\\\"Cancelar lembretes\\\",\\\"EventDisplay_Reminder_IgnoreEvent_ttip\\\":\\\"Ignorar um evento far\",\n    \" com que o Steam exclua este evento de sugest\",\n    \"es e recomenda\",\n    \"es futuras.\\\",\\\"EventDisplay_Reminder_FollowEvent_Error\\\":\\\"Erro ao seguir evento\\\",\\\"EventDisplay_Reminder_FollowEvent_ErrorDesc\\\":\\\"Ocorreu um erro ao tentar seguir o evento:\\\",\\\"EventDisplay_Reminder_IgnoreEvent_Error\\\":\\\"Erro ao ignorar evento\\\",\\\"EventDisplay_Reminder_IgnoreEvent_ErrorDesc\\\":\\\"Ocorreu um erro ao tentar ignorar o evento:\\\",\\\"EventDisplay_Reminder_Toast\\\":\\\"Enviar notifica\",\n    \"o no Steam quando come\",\n    \"ar\\\",\\\"EventDisplay_Reminder_AddToCalendar\\\":\\\"Adicionar ao calend\",\n    \"rio ou agenda\\\",\\\"EventDisplay_Reminder_AddToApple\\\":\\\"Adicionar ao Calend\",\n    \"rio da Apple\\\",\\\"EventDisplay_Reminder_AppleCalendar_Short\\\":\\\"Apple\\\",\\\"EventDisplay_Reminder_AddToGoogle\\\":\\\"Adicionar ao Google Agenda\\\",\\\"EventDisplay_Reminder_GoogleCalendar_Short\\\":\\\"Google\\\",\\\"EventDisplay_Reminder_AddToOutlook\\\":\\\"Adicionar ao Calend\",\n    \"rio do Outlook\\\",\\\"EventDisplay_Reminder_OutlookCalendar_Short\\\":\\\"Outlook\\\",\\\"EventDisplay_Reminder_AddToYahoo\\\":\\\"Adicionar ao Yahoo Agenda\\\",\\\"EventDisplay_Reminder_Preferences\\\":\\\"Editar prefer\",\n    \"ncias de lembretes...\\\",\\\"EventDidplay_Reminder_EventNotVisible\\\":\\\"O evento \\\\\\\\\\\"%1$\\\\\\\\\\\" n\",\n    \"o est\",\n    \" vis\",\n    \"vel, portanto, o lembrete n\",\n    \"o ser\",\n    \" exibido.\\\",\\\"EventDisplay_TimeDisplay\\\":\\\"De %1$s a %2$s\\\",\\\"EventDisplay_TimeDisplayNone\\\":\\\"Sem informa\",\n    \"es de data e hora\\\",\\\"EventDisplay_TimeBeginsOn\\\":\\\"Evento inicia\\\",\\\"EventDisplay_TimeBeginsOn_Past\\\":\\\"Iniciado\\\",\\\"EventDisplay_TimeBeginsOn_StartAndEnd_Past\\\":\\\"Evento come\",\n    \"ou\\\",\\\"EventDisplay_TimeEndsOn\\\":\\\"Termina\\\",\\\"EventDisplay_TimeEndsOn_Past\\\":\\\"Terminou\\\",\\\"EventDisplay_RunsForDuration\\\":\\\"Dura\",\n    \"o: %1$s\\\",\\\"EventDisplay_TimeLeft\\\":\\\"Termina em %1$s\\\",\\\"EventDisplay_TimeEndsOn_Ran\\\":\\\"Dura\",\n    \"o:\\\",\\\"EventDisplay_TimeRange\\\":\\\"Dura\",\n    \"o do evento\\\",\\\"EventDisplay_TimeInPast\\\":\\\"Publicado em\\\",\\\"EventDisplay_TimeUpcoming\\\":\\\"A partir de\\\",\\\"EventDisplay_EventUpcoming_WithDateAndTime\\\":\\\"A partir de %1$s, \",\n    \"s %2$s\\\",\\\"EventDisplay_TimeEventActive\\\":\\\"Evento em andamento\\\",\\\"EventDisplay_TimeEventOnNow\\\":\\\"Acontecendo agora!\\\",\\\"EventDisplay_Share_WithFriendsHeader\\\":\\\"Compartilhar com amigos\\\",\\\"EventDisplay_Share_LanguageLabel\\\":\\\"Compartilhar conte\",\n    \"do em:\\\",\\\"EventDisplay_Share_Link\\\":\\\"Link: \\\",\\\"EventDisplay_Share_OnMyStatus\\\":\\\"Editar e compartilhar status\\\",\\\"EventDisplay_Share_OnMyStatus_Details\\\":\\\"Publique esse status no feed de atividades. O Steam incluir\",\n    \" a mensagem e a pr\",\n    \"-visualiza\",\n    \"o exibida abaixo.\\\",\\\"EventDisplay_Share_OnMyStatus_Placeholder\\\":\\\"Diga algo sobre isso aos seus amigos...\\\",\\\"EventDisplay_Share_OnSteam\\\":\\\"Compartilhar na Comunidade Steam como uma atualiza\",\n    \"o de status\\\",\\\"EventDisplay_Share_OnFaceBook\\\":\\\"Compartilhar no Facebook\\\",\\\"EventDisplay_Share_OnTwitter\\\":\\\"Compartilhar no Twitter\\\",\\\"EventDisplay_Share_OnReddit\\\":\\\"Compartilhar no Reddit\\\",\\\"EventDisplay_Share_Success\\\":\\\"Sucesso!\\\",\\\"EventDisplay_Share_Failure\\\":\\\"Ocorreu um erro com a seguinte mensagem: \\\",\\\"EventDisplay_Share_Announcement\\\":\\\"An\",\n    \"ncio de %1$s\\\",\\\"EventDisplay_Share_Event\\\":\\\"Evento de %1$s\\\",\\\"EventDisplay_Share_NotLoggedIn\\\":\\\"Sess\",\n    \"o iniciada\\\",\\\"EventDisplay_Share_NotLoggedIn_Description\\\":\\\"Inicie a sess\",\n    \"o para usar este recurso\\\",\\\"EventDisplay_Share_CommentMigrationInProcess\\\":\\\"As discuss\",\n    \"es para este evento est\",\n    \"o temporariamente inacess\",\n    \"veis enquanto s\",\n    \"o transferidas para o sistema de eventos. Tente novamente mais tarde.\\\",\\\"EventDisplay_Share_OpenActivityFeed\\\":\\\"Abrir feed de atividade\\\",\\\"EventDisplay_AreYouSure\\\":\\\"Tem certeza de que deseja excluir este evento (%1$s)? Esta a\",\n    \"o pode ser desfeita.\\\",\\\"EventDisplay_AreYouSure_Visible\\\":\\\"Tem certeza de que deseja excluir este evento (%1$s)? Esta a\",\n    \"o pode ser desfeita. O evento ser\",\n    \" removido de todos os lugares dentro de alguns minutos.\\\",\\\"EventDisplay_DeleteEvent_InProgress\\\":\\\"Exclus\",\n    \"o em progresso. Por favor, aguarde.\\\",\\\"EventDisplay_DeleteEvent_Error\\\":\\\"Houve um erro ao processar a solicita\",\n    \"o de exclus\",\n    \"o:\\\",\\\"EventDisplay_DeleteEvent_ForumTopicError\\\":\\\"O evento foi exclu\",\n    \"do com sucesso. No entanto, houve um problema ao excluir o t\",\n    \"pico do evento no f\",\n    \"rum. \",\n    \" poss\",\n    \"vel tentar novamente no site %1$s. Detalhes do erro:\\\",\\\"EventDisplay_DeleteEvent_Success\\\":\\\"O evento foi exclu\",\n    \"do com sucesso.\\\",\\\"EventDisplay_DeleteEvent_Comment\\\":\\\"Tamb\",\n    \"m excluir o t\",\n    \"pico do evento no f\",\n    \"rum?\\\",\\\"EventDisplay_SocialTitle\\\":\\\"Tamb\",\n    \"m estamos aqui:\\\",\\\"EventDisplay_Sketchfab\\\":\\\"Modelo do Sketchfab\\\",\\\"EventDisplay_SketchFab_Error_Network\\\":\\\"N\",\n    \"o foi poss\",\n    \"vel contatar o Sketchfab\\\",\\\"EventEditor_Publish_VisibleNow\\\":\\\"Tornar vis\",\n    \"vel agora\\\",\\\"EventEditor_Publish_VisibleNow_ttip\\\":\\\"O evento ficar\",\n    \" vis\",\n    \"vel automaticamente no hor\",\n    \"rio agendado. Este bot\",\n    \"o for\",\n    \"a o evento a ficar vis\",\n    \"vel imediatamente.\\\",\\\"EventEditor_Edit\\\":\\\"Editar evento\\\",\\\"EventDisplay_DeleteEvent\\\":\\\"Excluir evento\\\",\\\"EventReminder_InProgress\\\":\\\"(as op\",\n    \"es de notifica\",\n    \"o aqui exibidas s\",\n    \"o ilustrativas e ainda n\",\n    \"o funcionam)\\\",\\\"EventReminder_NotifyByEmail\\\":\\\"Notifique-me por e-mail\\\",\\\"EventReminder_NotifyByEmail_ttip\\\":\\\"O Steam enviar\",\n    \" uma notifica\",\n    \"o para o seu e-mail quando o evento come\",\n    \"ar.\\\",\\\"EventReminder_NotifyByMobile\\\":\\\"Notifique-me no meu celular\\\",\\\"EventReminder_NotifyByMobile_ttip\\\":\\\"Quando o evento come\",\n    \"ar, o Steam enviar\",\n    \" uma notifica\",\n    \"o a todos os dispositivos com o aplicativo m\",\n    \"vel do Steam instalado e associado \",\n    \" sua conta.\\\",\\\"EventReminder_NotifyByEmail_Missing\\\":\\\"Verifique o seu endere\",\n    \"o de e-mail para receber lembretes.\\\",\\\"EventReminder_NotifyByEmail_Missing_Add\\\":\\\"Verifique o seu endere\",\n    \"o de e-mail.\\\",\\\"EventReminder_NotifyByMobile_Missing\\\":\\\"Instale um dos aplicativos do Steam para receber lembretes no seu dispositivo m\",\n    \"vel. \\\",\\\"EventReminder_NotifyByMobile_Install\\\":\\\"Conhe\",\n    \"a-os aqui.\\\",\\\"EventEmail_Subject_NewUpdate\\\":\\\"%1$s: nova atualiza\",\n    \"o\\\",\\\"EventEmail_Subject_UpcomingLaunch\\\":\\\"%1$s: lan\",\n    \"amento futuro\\\",\\\"EventEmail_Subject_NowAvailable\\\":\\\"%1$s j\",\n    \" dispon\",\n    \"vel\\\",\\\"EventEmail_Subject_FreeDemoAvailable\\\":\\\"Demonstra\",\n    \"o gratuita de %1$s j\",\n    \" dispon\",\n    \"vel\\\",\\\"EventEmail_Subject_SpecialOffer\\\":\\\"%1$s: oferta especial\\\",\\\"EventEmail_Subject_Tournament_Now\\\":\\\"%1$s: torneio ao vivo\\\",\\\"EventEmail_Subject_LiveStream_Now\\\":\\\"%1$s: transmiss\",\n    \"o ao vivo\\\",\\\"EventEmail_Subject_NewDLC\\\":\\\"%1$s: novo conte\",\n    \"do adicional dispon\",\n    \"vel\\\",\\\"EventEmail_Subject_NewExpansion\\\":\\\"%1$s: nova expans\",\n    \"o dispon\",\n    \"vel\\\",\\\"EventEmail_Subject_NewChapter\\\":\\\"%1$s: cap\",\n    \"tulo in\",\n    \"dito dispon\",\n    \"vel\\\",\\\"EventEmail_Subject_NewBattlePass\\\":\\\"%1$s: novo passe de batalha dispon\",\n    \"vel\\\",\\\"EventEmail_Subject_NewSeason\\\":\\\"%1$s: nova temporada dispon\",\n    \"vel\\\",\\\"EventEmail_Subject_NowFree\\\":\\\"%1$s: agora gratuito\\\",\\\"Email_Wishlist_NewReleaseEA_Subject\\\":\\\"%1$s j\",\n    \" est\",\n    \" dispon\",\n    \"vel em acesso antecipado no Steam!\\\",\\\"EventEmail_Button_ClickForMoreDetails\\\":\\\"Saiba mais\\\",\\\"Event_Button_VisitSalePage\\\":\\\"Visitar a p\",\n    \"gina\\\",\\\"EventEmail_Button_PrepurchaseNow\\\":\\\"Compre j\",\n    \" na pr\",\n    \"-venda!\\\",\\\"EventEmail_Button_BuyNow\\\":\\\"Compre j\",\n    \"!\\\",\\\"EventEmail_Button_PlayNow\\\":\\\"Jogue agora!\\\",\\\"EventEmail_Button_WishlistNow\\\":\\\"+ Lista de desejos\\\",\\\"EventEmail_WatchNow\\\":\\\"Assista j\",\n    \"\\\",\\\"EventEmail_Destination_Store\\\":\\\"P\",\n    \"gina do Jogo na Loja Steam\\\",\\\"EventEmail_Destination_Event\\\":\\\"P\",\n    \"gina de detalhes do evento\\\",\\\"EventEmail_Destination_SalesPage\\\":\\\"P\",\n    \"gina de promo\",\n    \"es da Loja Steam\\\",\\\"EventEmail_Button_BuyWithoutPSU\\\":\\\"Comprar sem fonte de alimenta\",\n    \"o\\\",\\\"EventEmail_Button_BuyWithoutPSUOutOfStock\\\":\\\"Comprar sem fonte de alimenta\",\n    \"o (esgotado)\\\",\\\"EventDashBoard_SummaryStats_Admin_Title\\\":\\\"(Vis\",\n    \"vel apenas para administradores)\\\",\\\"EventDashBoard_SummaryStats_Title\\\":\\\"Impress\",\n    \"es e visualiza\",\n    \"es diferentes\\\",\\\"EventDashBoard_SummaryStats_Desc\\\":\\\"(Beta) Estas s\",\n    \"o as impress\",\n    \"es e visualiza\",\n    \"es dos seus eventos e an\",\n    \"ncios por usu\",\n    \"rios \",\n    \"nicos com sess\",\n    \"o iniciada. Exibe apenas eventos e an\",\n    \"ncios novos criados com este editor.\\\",\\\"EventDashBoard_SummaryStats_Link\\\":\\\"Clique aqui para mais detalhes.\\\",\\\"EventDashBoard_SummaryStats_TotalImpressions\\\":\\\"Total de impress\",\n    \"es diferentes:\\\",\\\"EventDashBoard_SummaryStats_TotalViews\\\":\\\"Total de visualiza\",\n    \"es diferentes:\\\",\\\"EventDashBoard_SummaryStats_Dec2020Note\\\":\\\"Aviso: devido ao tr\",\n    \"fego elevado, a visibilidade foi significativamente subnotificada no per\",\n    \"odo de 23 de dezembro de 2020 a 5 de janeiro de 2021.\\\",\\\"EventDashBoard_ModerationQueueWarning\\\":\\\"Este evento n\",\n    \"o est\",\n    \" vis\",\n    \"vel na biblioteca porque ainda n\",\n    \"o foi analisado pela modera\",\n    \"o.\\\",\\\"EventDashBoard_Summary_LibraryHome_Shown\\\":\\\"Impress\",\n    \"es de eventos (imagem de capa):\\\",\\\"EventDashBoard_Summary_LibraryHome_Read\\\":\\\"Cliques em um evento para ver mais detalhes:\\\",\\\"EventDashBoard_Summary_AppDetailSpotlight_Shown\\\":\\\"Impress\",\n    \"es do banner de destaque:\\\",\\\"EventDashBoard_Summary_AppDetailSpotlight_Read\\\":\\\"Cliques em um banner de destaque para ver mais detalhes:\\\",\\\"EventDashBoard_Summary_AppDetailActivity_Shown\\\":\\\"Impress\",\n    \"es de eventos no feed de atividade:\\\",\\\"EventDashBoard_Summary_AppDetailActivity_Read\\\":\\\"Cliques em um evento para ver mais detalhes:\\\",\\\"EventDashBoard_Summary_StoreAppPage_Shown\\\":\\\"Impress\",\n    \"es de eventos (imagem de capa):\\\",\\\"EventDashBoard_Summary_StoreAppPage_Read\\\":\\\"Cliques em um evento para ver mais detalhes:\\\",\\\"EventDashBoard_Summary_Community_Shown\\\":\\\"Impress\",\n    \"es do resumo do evento:\\\",\\\"EventDashBoard_Summary_Community_Read\\\":\\\"Cliques no resumo do evento para ver mais detalhes:\\\",\\\"EventDashBoard_Summary_NewsHub_Shown\\\":\\\"Impress\",\n    \"es de evento na central de not\",\n    \"cias:\\\",\\\"EventDashBoard_Summary_NewsHub_Read\\\":\\\"Cliques em um evento para ver detalhes:\\\",\\\"EventDashBoard_Location_LibraryHome\\\":\\\"P\",\n    \"gina inicial da biblioteca\\\",\\\"EventDashBoard_Location_LibraryDetail\\\":\\\"P\",\n    \"gina do jogo na biblioteca\\\",\\\"EventDashBoard_Location_StoreDetail\\\":\\\"P\",\n    \"gina do jogo na loja\\\",\\\"EventDashBoard_Location_CommunityDetail\\\":\\\"Central da comunidade do aplicativo\\\",\\\"EventDashBoard_Location_PopUpViews\\\":\\\"Visualiza\",\n    \"es do pop-up do evento\\\",\\\"EventDashBoard_Location_NewsHubDetail\\\":\\\"Central de not\",\n    \"cias\\\",\\\"Sale_EnterEventsURL_Common\\\":\\\"Informe o URL do evento desejado\\\",\\\"Sale_EnterEventsURL_Tooltip_Common\\\":\\\"Informe o URL completo do evento e ent\",\n    \"o selecione a partir do menu de preenchimento autom\",\n    \"tico. O evento precisa estar publicamente vis\",\n    \"vel para ser adicionado.\\\",\\\"EventRepost_Dialog_Title\\\":\\\"Republicar evento\\\",\\\"EventRepost_Dialog_OK\\\":\\\"Republicar\\\",\\\"EventRepost_Dialog_Desc\\\":\\\"\\\\\\\\\\\"Republicar\\\\\\\\\\\" significa referenciar o evento da central de not\",\n    \"cias na linha do tempo dos grupos escolhidos abaixo. Abaixo, est\",\n    \"o os grupos da comunidade ou aplicativos nos quais este evento pode ser republicado. Escolha um ou mais grupos para publicar.\\\",\\\"EventRepost_Dialog_Existing\\\":\\\"%1$s \",\n    \" Grupo com republica\",\n    \"o\\\",\\\"EventRepost_Dialog_Action_Desc\\\":\\\"Ao clicar em OK, faremos o seguinte:\\\",\\\"EventRepost_Dialog_Action_Add\\\":\\\"O evento ser\",\n    \" republicado %1$s grupo(s)\\\",\\\"EventRepost_Dialog_Action_Remove\\\":\\\"A republica\",\n    \"o ser\",\n    \" removida de %1$s grupo(s)\\\",\\\"EventRepost_Dialog_Progress\\\":\\\"Republicando %1$s de %2$s itens\\\",\\\"EventRepost_Dialog_ResultFail\\\":\\\"Falha ao republicar. Tente novamente mais tarde.\\\",\\\"EventRepost_Dialog_ResultSuccess\\\":\\\"Republica\",\n    \"o bem-sucedida.\\\",\\\"EventDashBoard_Location_ModerationTitle\\\":\\\"Sobre modera\",\n    \"o de eventos\\\",\\\"EventDashBoard_Location_WaitingModeraion\\\":\\\"Visibilidade pendente de modera\",\n    \"o\\\",\\\"EventDisplay_ReferencedApps_Joiner\\\":\\\", \\\",\\\"EventDisplay_ReferencedApps\\\":\\\"Conte\",\n    \"do referenciado: %2$s.\\\",\\\"EventDisplay_ReferencedApps_Plural\\\":\\\"Conte\",\n    \"do referenciado: %2$s.\\\",\\\"EventEditor_SaleValveApproval_Title\\\":\\\"Essa p\",\n    \"gina s\",\n    \" pode ser colocada no ar ap\",\n    \"s an\",\n    \"lise da Valve\\\",\\\"EventEditor_SaleValveApproval_Title_Pending\\\":\\\"Evento promocional pendente de aprova\",\n    \"o pela Valve\\\",\\\"EventEditor_SaleValveApproval_Desc\\\":\\\"Use o bot\",\n    \" direita para enviar a sua p\",\n    \"gina para aprova\",\n    \"o com, no m\",\n    \"nimo, sete dias de anteced\",\n    \"ncia da data de publica\",\n    \"o desejada para garantir que haja tempo necess\",\n    \"rio para an\",\n    \"lise/aprova\",\n    \"o, e para que as altera\",\n    \"es necess\",\n    \"rias possam ser feitas.\\\",\\\"EventEditor_SaleValveApproval_Desc_Pending\\\":\\\"A equipe do Steam entrar\",\n    \" em contato com voc\",\n    \" pelo chamado do suporte do Steamworks caso seja necess\",\n    \"rio realizar altera\",\n    \"es na p\",\n    \"gina. Clique no bot\",\n    \" direita para acessar o chamado e adicionar coment\",\n    \"rios.\\\",\\\"EventEditor_SaleValveApproval_Admin_Tooltip\\\":\\\"Marcar a p\",\n    \"gina como aprovada permitir\",\n    \" que o parceiro publique a promo\",\n    \"o e coloque-a no ar.\\\",\\\"EventEditor_SaleValveApproval_Request_Button\\\":\\\"Solicitar an\",\n    \"lise...\\\",\\\"EventEditor_SaleValveApproval_Request_Approval\\\":\\\"Solicitar an\",\n    \"lise\\\",\\\"EventEditor_SaleValveApproval_Request_Approval_ttip\\\":\\\"Abre um chamado para solicitar uma an\",\n    \"lise para aprova\",\n    \"o de publica\",\n    \"o de p\",\n    \"gina promocional. Isso deve ser feito quando a p\",\n    \"gina estiver com as artes finais e incluir todos os jogos que deseja destacar.\\\",\\\"EventEditor_SaleValveApproval_Request_Desc\\\":\\\"Isso criar\",\n    \" um chamado no suporte do Steamworks solicitando que a Valve analise a sua p\",\n    \"gina promocional. Fa\",\n    \"a a solicita\",\n    \"o apenas ap\",\n    \"s finalizar a arte, textos e lista de jogos.\\\",\\\"EventEditor_SaleValveApproval_Request_Desc2\\\":\\\"Certifique-se de que o t\",\n    \"tulo e o prop\",\n    \"sito do evento estejam claramente descritos na parte superior da p\",\n    \"gina. Para exposi\",\n    \"es, pode ser necess\",\n    \"rio adicionar uma se\",\n    \"o textual no in\",\n    \"cio para descrever a exposi\",\n    \"o e o seu formato.\\\",\\\"EventEditor_SaleValveApproval_Request_Desc3\\\":\\\"A p\",\n    \"gina promocional ser\",\n    \" bloqueada para edi\",\n    \"es ap\",\n    \"s a an\",\n    \"lise. Para realizar altera\",\n    \"es ap\",\n    \"s a an\",\n    \"lise ou o in\",\n    \"cio do evento, inclua-as nos coment\",\n    \"rios e por que n\",\n    \"o foram conclu\",\n    \"das antes da an\",\n    \"lise.\\\",\\\"EventEditor_SaleValveApproval_Request_InputText\\\":\\\"Opcional: informa\",\n    \"es que deseja incluir para a equipe de an\",\n    \"lise\\\",\\\"EventEditor_SaleValveApproval_Request_Partner\\\":\\\"Escolha os parceiros cujos membros tamb\",\n    \"m poder\",\n    \"o acessar o chamado\\\",\\\"EventEditor_SaleValveApproval_Request_Partner_ttip\\\":\\\"Opcional: os outros membros dos parceiros escolhidos poder\",\n    \"o acessar e responder ao chamado. Por padr\",\n    \"o, apenas voc\",\n    \" poder\",\n    \" ler, atualizar e responder ao chamado aberto.\\\",\\\"EventEditor_SaleValveApproval_Request_Error\\\":\\\"Falha ao abrir o chamado. Tente novamente mais tarde.\\\",\\\"EventEditor_SaleValveApproval_Request_DuplicateError\\\":\\\"N\",\n    \"o foi poss\",\n    \"vel criar um novo chamado, pois um do mesmo tipo j\",\n    \" existe. Conclua a an\",\n    \"lise da sua outra p\",\n    \"gina promocional antes de enviar esta, ou atualize o chamado existente para tamb\",\n    \"m incluir a an\",\n    \"lise desta p\",\n    \"gina.\\\",\\\"EventEditor_SaleValveApproval_Request_Success\\\":\\\"Chamado aberto com sucesso!\\\",\\\"EventEditor_SaleValveApproval_Request_Link\\\":\\\"Ver chamado da an\",\n    \"lise...\\\",\\\"EventEditor_SaleValveApproval_Approved_Title\\\":\\\"P\",\n    \"gina aprovada e pronta para publica\",\n    \"o\\\",\\\"EventEditor_SaleValveApproval_Approved_Desc\\\":\\\"Troque para a aba \\\\\\\\\\\"Publicar\\\\\\\\\\\" para iniciar o processo de publica\",\n    \"o.\\\",\\\"EventEditor_SaleValveApproval_Approved_Desc_OnPublish\\\":\\\"Verifique as configura\",\n    \"es de visibilidade abaixo antes de publicar.\\\",\\\"AddToWishlist_short\\\":\\\"+ Lista de desejos\\\",\\\"Wishlisted\\\":\\\"Na lista de desejos\\\",\\\"Wishlisted_short\\\":\\\"Lista de desejos\\\",\\\"AddToWishlist_ttip\\\":\\\"Adicione \",\n    \" sua lista de desejos. Receba uma notifica\",\n    \"o por e-mail quando itens na sua lista de desejos forem lan\",\n    \"ados ou estiverem em promo\",\n    \"o.\\\",\\\"RemoveFromWishlist_ttip\\\":\\\"Este item j\",\n    \" est\",\n    \" na sua lista de desejos. Receba uma notifica\",\n    \"o por e-mail quando itens na sua lista de desejos forem lan\",\n    \"ados ou estiverem em promo\",\n    \"o.\\\",\\\"Wishlist_Error\\\":\\\"Erro ao atualizar lista de desejos\\\",\\\"Wishlist_Error_Desc\\\":\\\"Ocorreu um erro ao adicionar o item \",\n    \" lista de desejos. Tente novamente mais tarde.\\\",\\\"WindowTitle_FriendsList\\\":\\\"Lista de amigos\\\",\\\"FriendsList_OfflineTitle\\\":\\\"ERRO\\\",\\\"FriendsList_OfflineOrFailure\\\":\\\"N\",\n    \"o foi poss\",\n    \"vel conectar-se \",\n    \" rede de amigos\\\",\\\"FriendsList_OfflineDetail\\\":\\\"Este erro pode indicar que a sua rede local est\",\n    \" off-line ou que os servidores da rede de amigos do Steam est\",\n    \"o indispon\",\n    \"veis no momento.\\\",\\\"FriendsList_SignedOut\\\":\\\"Conversa Steam indispon\",\n    \"vel\\\",\\\"FriendsList_SignedOut_Detail\\\":\\\"Voc\",\n    \" est\",\n    \" off-line. Conecte-se para acessar a sua lista de amigos e conversar.\\\",\\\"FriendsList_OfflineMode\\\":\\\"Conversa Steam indispon\",\n    \"vel\\\",\\\"FriendsList_OfflineMode_Detail\\\":\\\"N\",\n    \" poss\",\n    \"vel ver a lista de amigos e conversar no modo off-line. Conecte-se para acess\",\n    \"-las.\\\",\\\"Friends_RetryLoading\\\":\\\"Tentar novamente\\\",\\\"Friends_SignIn\\\":\\\"Iniciar sess\",\n    \"o\\\",\\\"FriendsList_Offline_Disconnected\\\":\\\"Desconectado(a)\\\",\\\"FriendsList_LoadingTitle\\\":\\\"CARREGANDO\\\",\\\"FriendsList_StillLoadingSummary\\\":\\\"Carregando rede de amigos...\\\",\\\"FriendsList_StillLoadingDetail\\\":\\\"O Steam est\",\n    \" tentando conectar-se \",\n    \" rede de amigos, o que pode levar alguns segundos.\\\",\\\"Dialog_On\\\":\\\"SIM\\\",\\\"Dialog_Off\\\":\\\"N\",\n    \"O\\\",\\\"Dialog_DefaultWindowTitle\\\":\\\"Janela de di\",\n    \"logo do Steam\\\",\\\"TimeInterval_XYears\\\":\\\"%1$s anos\\\",\\\"TimeInterval_1YearXMonths\\\":\\\"1 ano e %1$s meses\\\",\\\"TimeInterval_1Year\\\":\\\"1 ano\\\",\\\"TimeInterval_XMonths\\\":\\\"%1$s meses\\\",\\\"TimeInterval_1Month\\\":\\\"1 m\",\n    \"s\\\",\\\"TimeInterval_1MonthX\\\":\\\"1 m\",\n    \"s e %1$s dias\\\",\\\"TimeInterval_XWeeks\\\":\\\"%1$s semanas \\\",\\\"TimeInterval_1Week\\\":\\\"1 semana\\\",\\\"TimeInterval_XDays\\\":\\\"%1$s dias\\\",\\\"TimeInterval_1Day\\\":\\\"1 dia\\\",\\\"TimeInterval_1DayXHours\\\":\\\"1 dia e %1$s horas\\\",\\\"TimeInterval_XHours\\\":\\\"%1$s horas\\\",\\\"TimeInterval_1Hour\\\":\\\"1 hora\\\",\\\"TimeInterval_1HourXMinutes\\\":\\\"1 hora e %1$s minutos\\\",\\\"TimeInterval_LessThanAnHour\\\":\\\"menos de uma hora\\\",\\\"TimeInterval_XMinutes\\\":\\\"%1$s minutos\\\",\\\"TimeInterval_XMinutesXSeconds\\\":\\\"%1$s minutos e %2$s segundos\\\",\\\"TimeInterval_XMinutes1Second\\\":\\\"%1$s minutos e 1 segundo\\\",\\\"TimeInterval_1Minute\\\":\\\"1 minuto\\\",\\\"TimeInterval_1MinuteXSeconds\\\":\\\"1 minuto e %1$s segundos\\\",\\\"TimeInterval_1Minute1Second\\\":\\\"1 minuto e 1 segundo\\\",\\\"TimeInterval_LessThanAMinute\\\":\\\"menos de um minuto\\\",\\\"TimeInterval_XSeconds\\\":\\\"%1$s segundos\\\",\\\"TimeInterval_1Second\\\":\\\"1 segundo\\\",\\\"TimeSince_XYears\\\":\\\"h\",\n    \" %1$s anos\\\",\\\"TimeSince_1YearXMonths\\\":\\\"h\",\n    \" 1 ano e %1$s meses\\\",\\\"TimeSince_1Year\\\":\\\"h\",\n    \" 1 ano\\\",\\\"TimeSince_XMonths\\\":\\\"h\",\n    \" %1$s meses\\\",\\\"TimeSince_1Month\\\":\\\"h\",\n    \" 1 m\",\n    \"s\\\",\\\"TimeSince_1MonthXDays\\\":\\\"h\",\n    \" 1 m\",\n    \"s e %1$s dias\\\",\\\"TimeSince_XWeeks\\\":\\\"h\",\n    \" %1$s semanas\\\",\\\"TimeSince_1Week\\\":\\\"h\",\n    \" 1 semana\\\",\\\"TimeSince_XDays\\\":\\\"h\",\n    \" %1$s dias\\\",\\\"TimeSince_1Day\\\":\\\"h\",\n    \" 1 dia\\\",\\\"TimeSince_1DayXHours\\\":\\\"h\",\n    \" 1 dia e %1$s horas\\\",\\\"TimeSince_XHours\\\":\\\"h\",\n    \" %1$s horas\\\",\\\"TimeSince_1Hour\\\":\\\"h\",\n    \" 1 hora\\\",\\\"TimeSince_1HourXMinutes\\\":\\\"h\",\n    \" 1 hora e %1$s minutos\\\",\\\"TimeSince_LessThanAnHour\\\":\\\"h\",\n    \" menos de uma hora\\\",\\\"TimeSince_XMinutes\\\":\\\"h\",\n    \" %1$s minutos\\\",\\\"TimeSince_XMinutesXSeconds\\\":\\\"h\",\n    \" %1$s minutos e %2$s segundos\\\",\\\"TimeSince_XMinutes1Second\\\":\\\"h\",\n    \" %1$s minutos e 1 segundo\\\",\\\"TimeSince_1Minute\\\":\\\"h\",\n    \" 1 minuto\\\",\\\"TimeSince_1MinuteXSeconds\\\":\\\"h\",\n    \" 1 minuto e %1$s segundos\\\",\\\"TimeSince_1Minute1Second\\\":\\\"h\",\n    \" 1 minuto e 1 segundo\\\",\\\"TimeSince_LessThanAMinute\\\":\\\"h\",\n    \" menos de 1 minuto\\\",\\\"TimeSince_XSeconds\\\":\\\"h\",\n    \" %1$s segundos\\\",\\\"TimeSince_1Second\\\":\\\"h\",\n    \" 1 segundo\\\",\\\"TimeSince_ThisWeek\\\":\\\"esta semana\\\",\\\"TimeRemaining_XYears\\\":\\\"%1$s anos restantes\\\",\\\"TimeRemaining_1YearXMonths\\\":\\\"1 ano e %1$s meses restantes\\\",\\\"TimeRemaining_1Year\\\":\\\"1 ano restante\\\",\\\"TimeRemaining_XMonths\\\":\\\"%1$s meses restantes\\\",\\\"TimeRemaining_1Month\\\":\\\"1 m\",\n    \"s restante\\\",\\\"TimeRemaining_1MonthXDays\\\":\\\"1 m\",\n    \"s e %1$s dias restantes\\\",\\\"TimeRemaining_XWeeks\\\":\\\"%1$s semanas restantes\\\",\\\"TimeRemaining_1Week\\\":\\\"1 semana restante\\\",\\\"TimeRemaining_XDays\\\":\\\"%1$s dias restantes\\\",\\\"TimeRemaining_1Day\\\":\\\"1 dia restante\\\",\\\"TimeRemaining_1DayXHours\\\":\\\"1 dia e %1$s horas restantes\\\",\\\"TimeRemaining_XHours\\\":\\\"%1$s horas restantes\\\",\\\"TimeRemaining_1Hour\\\":\\\"1 hora restante\\\",\\\"TimeRemaining_1HourXMinutes\\\":\\\"1 hora e %1$s minutos restantes\\\",\\\"TimeRemaining_LessThanAnHour\\\":\\\"menos de uma hora restante\\\",\\\"TimeRemaining_XMinutes\\\":\\\"%1$s minutos restantes\\\",\\\"TimeRemaining_XMinutesXSeconds\\\":\\\"%1$s minutos e %2$s segundos restantes\\\",\\\"TimeRemaining_XMinutes1Second\\\":\\\"%1$s minutos e 1 segundo restantes\\\",\\\"TimeRemaining_1Minute\\\":\\\"1 minuto restante\\\",\\\"TimeRemaining_1MinuteXSeconds\\\":\\\"1 minuto e %1$s segundos restantes\\\",\\\"TimeRemaining_1Minute1Second\\\":\\\"1 minuto e 1 segundo restantes\\\",\\\"TimeRemaining_LessThanAMinute\\\":\\\"menos de um minuto restante\\\",\\\"TimeRemaining_XSeconds\\\":\\\"%1$s segundos restantes\\\",\\\"TimeRemaining_1Second\\\":\\\"1 segundo restante\\\",\\\"TimeRemaining_ThisWeek\\\":\\\"esta semana\\\",\\\"Time_Now\\\":\\\"No ar\\\",\\\"Time_UpNext\\\":\\\"A seguir\\\",\\\"Time_Today\\\":\\\"hoje\\\",\\\"Time_Tomorrow\\\":\\\"amanh\",\n    \"\\\",\\\"Time_Yesterday\\\":\\\"ontem\\\",\\\"Time_Recent\\\":\\\"Recente\\\",\\\"Time_Today_At\\\":\\\"hoje, \",\n    \"s %1$s\\\",\\\"Time_Yesterday_At\\\":\\\"ontem, \",\n    \"s %1$s\\\",\\\"Time_Past_At\\\":\\\"%1$s, \",\n    \"s %2$s\\\",\\\"Time_QuarterOfYear_Q1\\\":\\\"1\",\n    \" trimestre de %1$s\\\",\\\"Time_QuarterOfYear_Q2\\\":\\\"2\",\n    \" trimestre de %1$s\\\",\\\"Time_QuarterOfYear_Q3\\\":\\\"3\",\n    \" trimestre de %1$s\\\",\\\"Time_QuarterOfYear_Q4\\\":\\\"4\",\n    \" trimestre de %1$s\\\",\\\"Time_QuarterOfYear_Expanded_Q1\\\":\\\"janeiro a mar\",\n    \"o de %1$s\\\",\\\"Time_QuarterOfYear_Expanded_Q2\\\":\\\"abril a junho de %1$s\\\",\\\"Time_QuarterOfYear_Expanded_Q3\\\":\\\"julho a setembro de %1$s\\\",\\\"Time_QuarterOfYear_Expanded_Q4\\\":\\\"outubro a dezembro de %1$s\\\",\\\"Store_ComingSoon_ComingSoon\\\":\\\"Em breve\\\",\\\"Store_ComingSoon_TBA\\\":\\\"A ser anunciada\\\",\\\"ContextMenu_Copy\\\":\\\"Copiar\\\",\\\"ContextMenu_Cut\\\":\\\"Recortar\\\",\\\"ContextMenu_Paste\\\":\\\"Colar\\\",\\\"ContextMenu_CopyLinkURL\\\":\\\"Copiar link\\\",\\\"ContextMenu_OpenLinkInNewWindow\\\":\\\"Abrir link em uma nova janela\\\",\\\"ContextMenu_CopyImageURL\\\":\\\"Copiar endere\",\n    \"o da imagem\\\",\\\"ContextMenu_OpenImageInNewWindow\\\":\\\"Abrir imagem em uma nova janela\\\",\\\"ContextMenu_AddToDictionary\\\":\\\"Adicionar \\\\\\\\\\\"%1$s\\\\\\\\\\\" ao dicion\",\n    \"rio\\\",\\\"Tooltip_Settings\\\":\\\"Gerenciar configura\",\n    \"es da lista de amigos\\\",\\\"Tooltip_VoiceSettings\\\":\\\"Gerenciar configura\",\n    \"es de voz\\\",\\\"Tooltip_CopyRemotePlayTogetherInviteURL\\\":\\\"Copiar URL de convite do Remote Play Together\\\",\\\"Tooltip_SearchFriends\\\":\\\"Buscar na minha lista\\\",\\\"Tooltip_AddFriend\\\":\\\"Adicionar amigo\\\",\\\"Tooltip_FriendRequest\\\":\\\"%1$s pedido de amizade pendente\\\",\\\"Tooltip_FriendRequest_Plural\\\":\\\"%1$s pedidos de amizade pendentes\\\",\\\"Tooltip_CreateGroupChat\\\":\\\"Criar sala de conversa\\\",\\\"Tooltip_InviteToGroup\\\":\\\"Convidar amigos para esta sala de conversa\\\",\\\"Tooltip_InviteToGroup_Denied\\\":\\\"Voc\",\n    \"o tem permiss\",\n    \"o para convidar usu\",\n    \"rios para esta sala\\\",\\\"Tooltip_GroupChatSettings\\\":\\\"Gerenciar configura\",\n    \"es da sala de conversa\\\",\\\"Tooltip_MemberCollapse\\\":\\\"Recolher lista de membros\\\",\\\"Tooltip_MemberExpand\\\":\\\"Expandir lista de membros\\\",\\\"Tooltip_ChatsCollapse\\\":\\\"Recolher lista de conversas\\\",\\\"Tooltip_ChatsExpand\\\":\\\"Expandir lista de conversas\\\",\\\"Tooltip_MinimizeList\\\":\\\"Recolher lista\\\",\\\"Tooltip_ExpandList\\\":\\\"Expandir lista\\\",\\\"Tooltip_PinChannelList\\\":\\\"Afixar lista de canais\\\",\\\"Tooltip_UnpinChannelList\\\":\\\"Desafixar lista de canais\\\",\\\"Tooltip_TextChannel\\\":\\\"Converse por texto com membros da sala\\\",\\\"Tooltip_TextChannelCreate\\\":\\\"Criar novo canal de texto\\\",\\\"Tooltip_NoPermissionChannelCreate\\\":\\\"Voc\",\n    \"o tem permiss\",\n    \"o para criar canais nesta sala\\\",\\\"Tooltip_VoiceChannel\\\":\\\"Converse por voz nestes canais\\\",\\\"Tooltip_VoiceChannelCreate\\\":\\\"Criar novo canal de voz\\\",\\\"Tooltip_DismissVoice\\\":\\\"Recusar convite de voz\\\",\\\"Tooltip_MicStatus_Active\\\":\\\"Microfone ativado\\\",\\\"Tooltip_MicStatus_Muted\\\":\\\"Microfone desativado\\\",\\\"Tooltip_RemoteMicStatus_Muted\\\":\\\"O usu\",\n    \"rio desativou o microfone\\\",\\\"Tooltip_MicStatus_NoMic\\\":\\\"O usu\",\n    \"rio n\",\n    \"o conectou um microfone\\\",\\\"Tooltip_RemoteOutputStatus_Muted\\\":\\\"O usu\",\n    \"rio desativou o \",\n    \"udio deste canal\\\",\\\"Tooltip_YourMicStatus_Muted\\\":\\\"Voc\",\n    \" desativou o microfone\\\",\\\"Tooltip_YourOutputStatus_Muted\\\":\\\"Voc\",\n    \" desativou o \",\n    \"udio deste canal\\\",\\\"Tooltip_VoiceControlButton_1v1_inactive\\\":\\\"Enviar convite de voz\\\",\\\"Tooltip_VoiceControlButton_1v1_active\\\":\\\"Sair do canal de voz\\\",\\\"Tooltip_VoiceControlButton_group_create\\\":\\\"Criar um canal de voz\\\",\\\"Tooltip_VoiceControlButton_group_leave\\\":\\\"Sair do canal de voz\\\",\\\"Tooltip_VoiceControlButton_group_joinsingle\\\":\\\"Entrar no canal de voz\\\",\\\"Tooltip_VoiceControlButton_group_joinmultiple\\\":\\\"Escolher uma canal de voz para juntar-se\\\",\\\"LanguageTitle\\\":\\\"Idioma\\\",\\\"Language_english\\\":\\\"Ingl\",\n    \"s\\\",\\\"Language_german\\\":\\\"Alem\",\n    \"o\\\",\\\"Language_french\\\":\\\"Franc\",\n    \"s\\\",\\\"Language_italian\\\":\\\"Italiano\\\",\\\"Language_korean\\\":\\\"Coreano\\\",\\\"Language_spanish\\\":\\\"Espanhol (Espanha)\\\",\\\"Language_schinese\\\":\\\"Chin\",\n    \"s simplificado\\\",\\\"Language_tchinese\\\":\\\"Chin\",\n    \"s tradicional\\\",\\\"Language_russian\\\":\\\"Russo\\\",\\\"Language_thai\\\":\\\"Tailand\",\n    \"s\\\",\\\"Language_japanese\\\":\\\"Japon\",\n    \"s\\\",\\\"Language_portuguese\\\":\\\"Portugu\",\n    \"s (Portugal)\\\",\\\"Language_polish\\\":\\\"Polon\",\n    \"s\\\",\\\"Language_danish\\\":\\\"Dinamarqu\",\n    \"s\\\",\\\"Language_dutch\\\":\\\"Holand\",\n    \"s\\\",\\\"Language_finnish\\\":\\\"Finland\",\n    \"s\\\",\\\"Language_norwegian\\\":\\\"Noruegu\",\n    \"s\\\",\\\"Language_swedish\\\":\\\"Sueco\\\",\\\"Language_hungarian\\\":\\\"H\",\n    \"ngaro\\\",\\\"Language_czech\\\":\\\"Tcheco\\\",\\\"Language_romanian\\\":\\\"Romeno\\\",\\\"Language_turkish\\\":\\\"Turco\\\",\\\"Language_arabic\\\":\\\"\",\n    \"rabe\\\",\\\"Language_brazilian\\\":\\\"Portugu\",\n    \"s (Brasil)\\\",\\\"Language_bulgarian\\\":\\\"B\",\n    \"lgaro\\\",\\\"Language_greek\\\":\\\"Grego\\\",\\\"Language_ukrainian\\\":\\\"Ucraniano\\\",\\\"Language_latam\\\":\\\"Espanhol (Am\",\n    \"rica Latina)\\\",\\\"Language_vietnamese\\\":\\\"Vietnamita\\\",\\\"Language_sc_schinese\\\":\\\"Steam China \",\n    \" chin\",\n    \"s simplificado\\\",\\\"Language_indonesian\\\":\\\"Indon\",\n    \"sio\\\",\\\"Language_koreana\\\":\\\"Coreano\\\",\\\"language_selection_none\\\":\\\"Nenhum idioma selecionado\\\",\\\"language_selection_english\\\":\\\"English (Ingl\",\n    \"s)\\\",\\\"language_selection_spanish\\\":\\\"Espa\",\n    \" Espa\",\n    \"a (Espanhol (Espanha))\\\",\\\"language_selection_french\\\":\\\"Fran\",\n    \"ais (Franc\",\n    \"s)\\\",\\\"language_selection_italian\\\":\\\"Italiano (Italiano)\\\",\\\"language_selection_german\\\":\\\"Deutsch (Alem\",\n    \"o)\\\",\\\"language_selection_greek\\\":\\\"\",\n    \" (Grego)\\\",\\\"language_selection_koreana\\\":\\\"\",\n    \" (Coreano)\\\",\\\"language_selection_korean\\\":\\\"\",\n    \" (Coreano)\\\",\\\"language_selection_schinese\\\":\\\"\",\n    \" (Chin\",\n    \"s Simplificado)\\\",\\\"language_selection_sc_schinese\\\":\\\"\",\n    \" (Chin\",\n    \"s simplificado)\\\",\\\"language_selection_tchinese\\\":\\\"\",\n    \" (Chin\",\n    \"s Tradicional)\\\",\\\"language_selection_russian\\\":\\\"\",\n    \" (Russo)\\\",\\\"language_selection_thai\\\":\\\"\",\n    \" (Tailand\",\n    \"s)\\\",\\\"language_selection_japanese\\\":\\\"\",\n    \" (Japon\",\n    \"s)\\\",\\\"language_selection_portuguese\\\":\\\"Portugu\",\n    \"s (Portugal)\\\",\\\"language_selection_brazilian\\\":\\\"Portugu\",\n    \"s (Brasil)\\\",\\\"language_selection_polish\\\":\\\"Polski (Polon\",\n    \"s)\\\",\\\"language_selection_danish\\\":\\\"Dansk (Dinamarqu\",\n    \"s)\\\",\\\"language_selection_dutch\\\":\\\"Nederlands (Holand\",\n    \"s)\\\",\\\"language_selection_finnish\\\":\\\"Suomi (Finland\",\n    \"s)\\\",\\\"language_selection_norwegian\\\":\\\"Norsk (Noruegu\",\n    \"s)\\\",\\\"language_selection_swedish\\\":\\\"Svenska (Sueco)\\\",\\\"language_selection_czech\\\":\\\"\",\n    \"tina (Tcheco)\\\",\\\"language_selection_hungarian\\\":\\\"Magyar (H\",\n    \"ngaro)\\\",\\\"language_selection_romanian\\\":\\\"Rom\",\n    \" (Romeno)\\\",\\\"language_selection_bulgarian\\\":\\\"\",\n    \"lgaro)\\\",\\\"language_selection_pirate\\\":\\\"Yarr! (Ingl\",\n    \"s Pirata)\\\",\\\"language_selection_turkish\\\":\\\"T\",\n    \"e (Turco)\\\",\\\"language_selection_ukrainian\\\":\\\"\",\n    \" (Ucraniano)\\\",\\\"language_selection_vietnamese\\\":\\\"Ti\",\n    \"ng Vi\",\n    \"t (Vietnamita)\\\",\\\"language_selection_arabic\\\":\\\"\",\n    \"rabe)\\\",\\\"language_selection_spanish_mexican\\\":\\\"Espa\",\n    \" Mexicano (Espanhol (M\",\n    \"xico))\\\",\\\"language_selection_latam\\\":\\\"Espa\",\n    \" Latinoam\",\n    \"rica (Espanhol (Am\",\n    \"rica Latina))\\\",\\\"language_selection_indonesian\\\":\\\"Bahasa Indonesia (Indon\",\n    \"sio)\\\",\\\"Bbcode_Originally_Posted_By\\\":\\\"Publicado originalmente por\\\",\\\"Bbcode_No_Match\\\":\\\"N\",\n    \"o corresponde a BBCode v\",\n    \"lido\\\",\\\"Bbcode_Expand_ShowMore_Collapsed\\\":\\\"Exibir mais\\\",\\\"Bbcode_Expand_ShowMore_Expanded\\\":\\\"Recolher\\\",\\\"Bbcode_Expand_Spoiler_Collapsed\\\":\\\"Exibir spoilers\\\",\\\"Bbcode_Expand_Spoiler_Expanded\\\":\\\"Ocultar spoilers\\\",\\\"Bbcode_Expand_Details_Collapsed\\\":\\\"Exibir detalhes\\\",\\\"Bbcode_Expand_Details_Expanded\\\":\\\"Ocultar detalhes\\\",\\\"Bbcode_Spoiler_Hide\\\":\\\"Ocultar spoiler\\\",\\\"Bbcode_Spoiler_Show\\\":\\\"Exibir spoiler\\\",\\\"Editor_Bold\\\":\\\"Negrito\\\",\\\"Editor_Underline\\\":\\\"Sublinhado\\\",\\\"Editor_Italics\\\":\\\"It\",\n    \"lico\\\",\\\"Editor_StrikeThrough\\\":\\\"Riscado\\\",\\\"Editor_Link\\\":\\\"Inserir link\\\",\\\"Editor_Unordered\\\":\\\"Lista n\",\n    \"o ordenada\\\",\\\"Editor_Ordered\\\":\\\"Lista ordenada\\\",\\\"Editor_Header\\\":\\\"Cabe\",\n    \"alho\\\",\\\"Editor_Header2\\\":\\\"Cabe\",\n    \"alho 2\\\",\\\"Editor_Header3\\\":\\\"Cabe\",\n    \"alho 3\\\",\\\"Editor_Emoticon\\\":\\\"Inserir emoticon\\\",\\\"EventEditor_ConvertHTML_Error\\\":\\\"N\",\n    \"o foi poss\",\n    \"vel converter o HTML\\\",\\\"EventEditor_ConvertHTML_Error_Desc\\\":\\\"Falha na convers\",\n    \"o de HTML para BBCode com o seguinte erro: \\\\\\\\\\\"%1$s\\\\\\\\\\\"\\\",\\\"EventEditor_InsertLinkURL\\\":\\\"Inserir URL\\\",\\\"EventEditor_FormattingHelp_GetHelpLink\\\":\\\"Ajuda de formata\",\n    \"o\\\",\\\"EventEditor_InsertTrailer\\\":\\\"Adicionar trailer de jogo\\\",\\\"EventEditor_InsertTrailer_SearchApp\\\":\\\"Buscar por nome ou AppID\\\",\\\"EventEditor_FailedToLoadApp\\\":\\\"Falha ao carregar detalhes do aplicativo. Tente novamente mais tarde. (%1$s)\\\",\\\"EventEditor_ImportHTML\\\":\\\"Importar HTML\\\",\\\"EventEditor_ImportFromHTML\\\":\\\"Importar de HTML\\\",\\\"EventEditor_ImportFromHTML_ttip\\\":\\\"Importar de HTML. Converter\",\n    \" automaticamente o seu HTML em marcadores de formata\",\n    \"o do Steam.\\\",\\\"EventEditor_ImportFromHTML_Instruction\\\":\\\"Digite ou cole o c\",\n    \"digo HTML abaixo.\\\",\\\"EventEditor_ImportFromHTML_PreserveNewlines\\\":\\\"Manter quebras de linha\\\",\\\"EventEditor_ImportFromHTML_PreserveNewlines_Hint\\\":\\\"Quebras de linha n\",\n    \"o costumam fazer efeito em HTML, mas em BBCode elas s\",\n    \"o exibidas como linhas em branco. Caso tenha usado marcadores <p> ou <br>, deixe a caixa desmarcada. Caso costume usar programas que adicionam marcadores <br> de forma autom\",\n    \"tica para quebras de linha, voc\",\n    \" provavelmente dever\",\n    \" marcar esta caixa.\\\",\\\"EventEditor_ImportFromHTML_ConvertToBBCode\\\":\\\"Converter para BBCode:\\\",\\\"EventEditor_ImportFromHTML_ConversionInProgress\\\":\\\"Convers\",\n    \"o em andamento. N\",\n    \"o feche essa janela.\\\",\\\"EventEditor_ImportFromHTML_ConvertFinished\\\":\\\"Convers\",\n    \"o conclu\",\n    \"da. Voc\",\n    \" pode fechar essa janela com seguran\",\n    \"a.\\\",\\\"EventEditor_InsertYouTube\\\":\\\"Inserir v\",\n    \"deo do YouTube\",\n    \"\\\",\\\"EventEditor_InsertYouTube_Left\\\":\\\"Alinhado \",\n    \" esquerda\\\",\\\"EventEditor_InsertYouTube_Right\\\":\\\"Alinhado \",\n    \" direita\\\",\\\"EventEditor_InsertYouTube_Full\\\":\\\"Largura completa\\\",\\\"EventEditor_InsertYouTube_URL\\\":\\\"URL completo\\\",\\\"EventEditor_InsertYouTube_Position\\\":\\\"Posi\",\n    \"o\\\",\\\"EventEditor_InsertYouTube_Placholder\\\":\\\"Informe um URL do YouTube\",\n    \"\\\",\\\"EventEditor_InsertYouTube_NoURL\\\":\\\"Informe um URL v\",\n    \"lido do YouTube\",\n    \".\\\",\\\"EventEditor_InsertYouTube_Summary\\\":\\\"Descri\",\n    \"o resumida\\\",\\\"EventEditor_InsertImage\\\":\\\"Inserir uma imagem da web\\\",\\\"EventEditor_InsertImage_Title\\\":\\\"Inserir imagem\\\",\\\"EventEditor_ReplaceImage_Title\\\":\\\"Substituir imagem\\\",\\\"EventEditor_InsertImage_Desc\\\":\\\"Informe o URL de uma imagem (por exemplo .jpg, .gif ou .png) para a inclu\",\n    \"-la na publica\",\n    \"o.\\\",\\\"EventEditor_InsertImage_URL\\\":\\\"URL da imagem\\\",\\\"EventEditor_InsertImage_Placeholder\\\":\\\"Informe um URL v\",\n    \"lido\\\",\\\"EventEditor_InsertImage_Anchor\\\":\\\"Opcional: URL a abrir ao clicar na imagem\\\",\\\"EventEditor_EditVideo_Title\\\":\\\"Incorporar v\",\n    \"deo\\\",\\\"EventEditor_InsertVideo_InputMP4\\\":\\\"URL do MP4\\\",\\\"EventEditor_InsertVideo_InputWebM\\\":\\\"URL do WebM\\\",\\\"EventEditor_InsertVideo_InputPoster\\\":\\\"URL do p\",\n    \"ster (opcional)\\\",\\\"EventEditor_InsertVideo_InputAutoplay\\\":\\\"Reproduzir automaticamente\\\",\\\"EventEditor_InsertVideo_InputShowControls\\\":\\\"Exibir controles\\\",\\\"EventEditor_AddSpeaker\\\":\\\"Adicionar palestrante\\\",\\\"EventEditor_AddSpeaker_Desc\\\":\\\"Adiciona os detalhes de um palestrante ou transmissor ao evento. Os detalhes ser\",\n    \"o exibidos no evento e no seu resumo como um widget.\\\",\\\"EventEditor_AddSpeaker_Name\\\":\\\"Nome:\\\",\\\"EventEditor_AddSpeaker_Title\\\":\\\"Cargo (opcional):\\\",\\\"EventEditor_AddSpeaker_Company\\\":\\\"Empresa (opcional):\\\",\\\"EventEditor_AddSpeaker_About\\\":\\\"Sobre os palestrantes:\\\",\\\"EventEditor_AddSpeaker_About_Placeholder\\\":\\\"Conte-nos sobre os palestrantes e transmissores... (pode incluir links para redes sociais)\\\",\\\"EventEditor_ChoosePhoto\\\":\\\"Escolher foto do(a) palestrante\\\",\\\"EventEditor_AssociateSteamAccount\\\":\\\"Conta Steam associada\\\",\\\"EventEditor_AssociateSteamAccount_ttip\\\":\\\"Ao associar a conta Steam apropriada ao palestrante, um \",\n    \"cone de apresentador ser\",\n    \" exibido na transmiss\",\n    \"o que aparece na p\",\n    \"gina da promo\",\n    \"o.\\\",\\\"EventEditor_SteamAccount_addme\\\":\\\"Associar a minha conta\\\",\\\"EventEditor_SteamAccount_addfriend\\\":\\\"Associar conta de amigo\\\",\\\"EventEditor_SteamAccount_clear\\\":\\\"Remover associa\",\n    \"o\\\",\\\"BBCode_ChooseImage\\\":\\\"Escolher imagem (%1$s x %2$s)\\\",\\\"BBCode_ResizeImage\\\":\\\"Redimensionar imagem\\\",\\\"EventEditor_LinkDescription\\\":\\\"Texto a ser exibido\\\",\\\"EventEditor_LinkURL\\\":\\\"URL\\\",\\\"EventEditor_YouTubeVideoTitle\\\":\\\"V\",\n    \"deo do YouTube\",\n    \": %1$s\\\",\\\"EventEditor_YouTubeVideoViews\\\":\\\"Visualiza\",\n    \"es: %1$s\\\",\\\"EventEditor_Author\\\":\\\"Por: %1$s\\\",\\\"EventEditor_Comments\\\":\\\"Coment\",\n    \"rios\\\",\\\"EventEditor_UpVotes\\\":\\\"Avalia\",\n    \"es positivas\\\",\\\"EventEditor_DownVotes\\\":\\\"Avalia\",\n    \"es negativas\\\",\\\"RSSManager_PostEvent_CreateFeedTitle\\\":\\\"Criar configura\",\n    \"es do feed de not\",\n    \"cias\\\",\\\"RSSManager_PostEvent_UpdateFeedTitle\\\":\\\"Atualizar configura\",\n    \"es do feed de not\",\n    \"cias\\\",\\\"RSSManager_PostEvent_Tilte\\\":\\\"Publicar no Steam?\\\",\\\"RSSManager_CreateFeed_Review\\\":\\\"Verifique os seguintes requisitos antes de continuar:\\\",\\\"RSSManager_PostEvent_CreateFeed_DuringPost\\\":\\\"O feed RSS pr\",\n    \"-visualizado n\",\n    \"o corresponde \",\n    \" configura\",\n    \"o atual. Antes da cria\",\n    \"o do novo evento, \",\n    \" necess\",\n    \"rio que o URL do feed RSS usado para a pr\",\n    \"-visualiza\",\n    \"o seja atualizado. Por padr\",\n    \"o, a automa\",\n    \"o do feed RSS estar\",\n    \" desativada. Isto pode ser alterado mais tarde.\\\",\\\"RSSManager_PostEvent_CreateFeed_Desc\\\":\\\"Criar/atualizar feed com este URL RSS?: \\\\\\\\\\\"%1$s\\\\\\\\\\\"\\\",\\\"RSSManager_PostEvent_Failure\\\":\\\"N\",\n    \"o foi poss\",\n    \"vel criar/atualizar o feed nem publicar a not\",\n    \"cia\\\",\\\"RSSManager_PostEvent_CreatePost\\\":\\\"Deseja publicar este an\",\n    \"ncio no Steam?\\\",\\\"RSSManager_PostEvent_CreatePost_Draft\\\":\\\"Salvar como rascunho? Em vez de publicar o an\",\n    \"ncio imediatamente, ele ser\",\n    \" criado como oculto e n\",\n    \"o publicado. Depois, voc\",\n    \" poder\",\n    \" realizar altera\",\n    \"es antes de public\",\n    \"-lo no painel de an\",\n    \"ncios.\\\",\\\"RSSManager_PostEvent_UpdatePost\\\":\\\"Este evento j\",\n    \" existe no Steam. Deseja substituir o conte\",\n    \"do pelo do feed RSS? \",\n    \"til caso o conte\",\n    \"do do feed RSS tenha sido alterado. Ao substituir o conte\",\n    \"do, quaisquer personaliza\",\n    \"es feitas no editor ser\",\n    \"o perdidas.\\\",\\\"RSSManager_PostEvent_InFlight\\\":\\\"Aguarde at\",\n    \" que o servidor do Steam conclua a a\",\n    \"o.\\\",\\\"RSSManager_PostEvent_Success_feed\\\":\\\"O feed RSS foi atualizado com sucesso\\\",\\\"RSSManager_PostEvent_Success\\\":\\\"An\",\n    \"ncio criado com sucesso. Para edit\",\n    \"-lo, acesse: \\\",\\\"RSSManager_PostEvent_EventLink\\\":\\\"Edite o evento aqui\\\",\\\"RSSManager_CreateFeed_Permissions_v1\\\":\\\"Recebi autoriza\",\n    \"o para permitir que este feed RSS seja guardado e redistribu\",\n    \"do pelo Steam.\\\",\\\"RSSManager_CreateFeed_Conduct_v1\\\":\\\"Confirmo que o conte\",\n    \"do deste feed RSS, a ser redistribu\",\n    \"do pelo Steam, segue o C\",\n    \"digo de Conduta On-line do Steam.\\\",\\\"RSSManager_CreateFeed_Conduct_Link\\\":\\\"Consulte o C\",\n    \"digo de Conduta On-line do Steam aqui.\\\",\\\"RSSManager_Status_Automation_Desc\\\":\\\"Publicar automaticamente an\",\n    \"ncios de not\",\n    \"cias a partir do feed RSS\\\",\\\"RSSManager_Status_Automation_Activate\\\":\\\"Ativar feed RSS\\\",\\\"RSSManager_Status_Automation_DisableFailed\\\":\\\"N\",\n    \"o foi poss\",\n    \"vel desativar o feed. Tente novamente mais tarde.\\\",\\\"RSSManager_EventDashBoard\\\":\\\"Abrir painel de eventos\\\",\\\"RSSManager_PostEvent_ViewEvent\\\":\\\"Ver evento\\\",\\\"RSSManager_PostEvent_EditEvent\\\":\\\"Editar evento\\\",\\\"RSSManager_PostEvent_UpdateEvent\\\":\\\"Substituir conte\",\n    \"do do evento pelo do feed RSS\\\",\\\"RSSManager_SeeReview\\\":\\\"Ver an\",\n    \"lise\\\",\\\"RSSManager_PostEvent_Draft\\\":\\\"Salvo como rascunho\\\",\\\"RSSManager_PostEvent_Staged\\\":\\\"Salvo como rascunho, ser\",\n    \" publicado automaticamente: %1$s\\\",\\\"RSSManager_PostEvent_PostedDate\\\":\\\"Publicado em %1$s\\\",\\\"RSSManager_PostEvent_ViewRaw\\\":\\\"Ver RSS original\\\",\\\"RSSManager_PreviewInfo\\\":\\\"Exibindo conte\",\n    \"do do RSS no URL \\\\\\\\\\\"%1$s\\\\\\\\\\\":\\\",\\\"Error_Message\\\":\\\"Mensagem de erro\\\",\\\"Warning_Message\\\":\\\"Mensagem de aviso\\\",\\\"Informational_Message\\\":\\\"Mensagem informativa\\\",\\\"Error_Description\\\":\\\"Ocorreu um erro (c\",\n    \"digo: %1$s) detalhes: (%2$s)\\\",\\\"Error_FailureNotice\\\":\\\"Falha\\\",\\\"Error_GenericFailureDescription\\\":\\\"Lamentamos, isso n\",\n    \"o funcionou.\\\",\\\"Image_ErrorTitle\\\":\\\"Falha ao carregar a imagem \\\\\\\\\\\"%1$s\\\\\\\\\\\", poss\",\n    \"veis erros incluem:\\\",\\\"Image_Error_msg1\\\":\\\"Confirme se o caminho da imagem est\",\n    \" correto.\\\",\\\"Image_Error_msg2\\\":\\\"Confirme se o servidor de hospedagem da imagem \",\n    \" compat\",\n    \"vel com acesso an\",\n    \"nimo. O console do navegador pode indicar um erro do tipo \\\\\\\\\\\"Access-Control-Allow-Origin\\\\\\\\\\\" caso incompat\",\n    \"vel.\\\",\\\"Image_Error_msg3\\\":\\\"Confirme que o URL da imagem come\",\n    \"a com https:// e n\",\n    \"o http://. Esperamos acessar as imagens por uma transfer\",\n    \"ncia criptografada.\\\",\\\"Image_Error_suggestion\\\":\\\"\",\n    \" poss\",\n    \"vel hospedar a imagem no Steam gratuitamente.\\\",\\\"Platform_Hint_Mobile\\\":\\\"em dispositivo m\",\n    \"vel\\\",\\\"Platform_Hint_BigPicture\\\":\\\"no Big Picture\\\",\\\"Platform_Hint_VR\\\":\\\"em Realidade Virtual\\\",\\\"Platform_Hint_SteamDeck\\\":\\\"no Steam Deck\\\",\\\"Hover_SteamLevel\\\":\\\"N\",\n    \"vel Steam\\\",\\\"Hover_BadgeXP\\\":\\\"%1$s XP\\\",\\\"PersonaStateOffline\\\":\\\"Off-line\\\",\\\"PersonaStateAway\\\":\\\"Ausente\\\",\\\"PersonaStateOnline\\\":\\\"Dispon\",\n    \"vel\\\",\\\"PersonaStateBlocked\\\":\\\"Bloqueado(a)\\\",\\\"PersonaStateInGame\\\":\\\"Em jogo\\\",\\\"PersonaStateBusy\\\":\\\"Ocupado(a)\\\",\\\"PersonaStateSnooze\\\":\\\"Ausente\\\",\\\"PersonaStateOnlineIngame\\\":\\\"Dispon\",\n    \"vel/Em jogo\\\",\\\"PersonaStatePartyBeacon\\\":\\\"Quer jogar\\\",\\\"PersonaStateInvisible\\\":\\\"Invis\",\n    \"vel\\\",\\\"PersonaStateInNonSteamGame\\\":\\\"Em jogo n\",\n    \"o Steam\\\",\\\"PersonaStateSignedOut\\\":\\\"Sess\",\n    \"o finalizada\\\",\\\"PersonaStateOfflineMode\\\":\\\"Modo off-line\\\",\\\"PersonaStateWatchingBroadcast\\\":\\\"Assistindo \",\n    \" transmiss\",\n    \"o:\\\",\\\"PersonaStateLookingToTrade\\\":\\\"Querendo trocar\\\",\\\"PersonaStateLookingToPlay\\\":\\\"Querendo jogar\\\",\\\"PersonaStateLastSeen\\\":\\\"\",\n    \"ltima vez on-line %1$s\\\",\\\"PersonaStateLastSeen_JustNow\\\":\\\"\",\n    \"ltima vez on-line agora h\",\n    \" pouco\\\",\\\"PersonaStateRemotePlayTogether\\\":\\\"Remote Play Together\\\",\\\"PersonaStateInvisibleDescriptor\\\":\\\"Aparecer off-line, mas ainda poder conversar\\\",\\\"PersonaStateSignedOutDescriptor\\\":\\\"Desconectar-se da lista e conversas\\\",\\\"PersonaStateDoNotDisturbDescriptor\\\":\\\"Desativa todas as notifica\",\n    \"es de conversa\\\",\\\"PersonaStateOfflineModeDescriptor\\\":\\\"N\",\n    \"o conectar-se aos servidores Steam\\\",\\\"User_WantsToPlay\\\":\\\"Entrar\\\",\\\"User_ToggleDoNotDisturb\\\":\\\"N\",\n    \"o perturbe\\\",\\\"User_GameInfoHidden\\\":\\\"Os detalhes do jogo est\",\n    \"o ocultados devido \",\n    \"s suas configura\",\n    \"es de privacidade\\\",\\\"User_LimitedAccount\\\":\\\"Sua conta n\",\n    \"o possui os requisitos necess\",\n    \"rios para usar este recurso. %1$s para mais informa\",\n    \"es.\\\",\\\"User_LimitedAccount_UrlInfo\\\":\\\"Acesse o Suporte Steam\\\",\\\"isNickname\\\":\\\"O apelido que voc\",\n    \" deu a este amigo\\\",\\\"Friend_Menu_NotAFriendLabel\\\":\\\"N\",\n    \"o amigos\\\",\\\"Friend_Menu_NotAFriendRequesting\\\":\\\"Enviou pedido de amizade\\\",\\\"DASHPlayerStats_BytesReceived\\\":\\\"Bytes recebidos:\\\",\\\"DASHPlayerStats_BufferingResolution\\\":\\\"Resolu\",\n    \"o em buffer:\\\",\\\"DASHPlayerStats_PlaybackResolution\\\":\\\"Resolu\",\n    \"o de reprodu\",\n    \"o:\\\",\\\"DASHPlayerStats_HtmlResolution\\\":\\\"Resolu\",\n    \"o de exibi\",\n    \"o:\\\",\\\"DASHPlayerStats_DroppedFrames\\\":\\\"Quadros descartados:\\\",\\\"DASHPlayerStats_VideoBuffered\\\":\\\"V\",\n    \"deo em buffer:\\\",\\\"DASHPlayerStats_AudioBuffered\\\":\\\"\",\n    \"udio em buffer:\\\",\\\"DASHPlayerStats_BandwidthRequired\\\":\\\"Largura de banda necess\",\n    \"ria (Mbps):\\\",\\\"DASHPlayerStats_BandwidthVideo\\\":\\\"Largura de banda do v\",\n    \"deo (Mbps):\\\",\\\"DASHPlayerStats_BandwidthNums\\\":\\\"Largura de banda m\",\n    \"n./m\",\n    \"x./m\",\n    \"d. (Mbps):\\\",\\\"DASHPlayerStats_DownloadNums\\\":\\\"Segundos p/ DL m\",\n    \"n./m\",\n    \"x./m\",\n    \"d.:\\\",\\\"DASHPlayerStats_ContentServer\\\":\\\"Servidor:\\\",\\\"DASHPlayerStats_ActiveDownloads\\\":\\\"Downloads ativos:\\\",\\\"DASHPlayerStats_StallEvents\\\":\\\"Eventos de espera:\\\",\\\"DASHPlayerStats_FailedDownloads\\\":\\\"Eventos de download com falha:\\\",\\\"DASHPlayerStats_VideoDownloadProgress\\\":\\\"Progresso de download do v\",\n    \"deo:\\\",\\\"DASHPlayerStats_TimeToFirstFrame\\\":\\\"Milissegundos at\",\n    \" quadro:\\\",\\\"DASHPlayerStats_DroppingFrames\\\":\\\"Quadros perdidos detectados:\\\",\\\"DASHPlayerStats_CurrentFPS\\\":\\\"Taxa de quadros atual:\\\",\\\"DASHPlayerStats_Tracking\\\":\\\"Coletando dados...\\\",\\\"DASHPlayerStats_PlaybackRate\\\":\\\"Velocidade de reprodu\",\n    \"o:\\\",\\\"DASHPlayerStats_VideoBufferRange\\\":\\\"Buffer de v\",\n    \"deo %1$s:\\\",\\\"DASHPlayerStats_AudioBufferRange\\\":\\\"Buffer de \",\n    \"udio %1$s:\\\",\\\"DASHPlayerStats_VideoNoRangeInformation\\\":\\\"Nenhum segmento de v\",\n    \"deo em buffer\\\",\\\"DASHPlayerStats_AudioNoRangeInformation\\\":\\\"Nenhum segmento de \",\n    \"udio em buffer\\\",\\\"DASHPlayerControls_GoLive\\\":\\\"Ao vivo\\\",\\\"DASHPlayerControls_IsLive\\\":\\\"Ao vivo\\\",\\\"DASHPlayerControls_ClickToPlay\\\":\\\"Clique para assistir\\\",\\\"DASHPlayerControls_IsReplay\\\":\\\"REPRISE\\\",\\\"DASHPlayerControls_Start\\\":\\\"In\",\n    \"cio\\\",\\\"DASHPlayerControls_End\\\":\\\"Fim\\\",\\\"Played_Minutes\\\":\\\"%1$s minutos\\\",\\\"Played_Hours\\\":\\\"%1$s horas\\\",\\\"WriteReview_Dialog_PostReview\\\":\\\"Publicar an\",\n    \"lise\\\",\\\"WriteReview_Dialog_ReviseReview\\\":\\\"Editar an\",\n    \"lise\\\",\\\"WriteReview_Dialog_Title\\\":\\\"An\",\n    \"lise\\\",\\\"WriteReview_Dialog_Playtime\\\":\\\"Voc\",\n    \" jogou por %1$s\\\",\\\"WriteReview_Dialog_Playtime_Software\\\":\\\"Voc\",\n    \" usou por %1$s\\\",\\\"WriteReview_Dialog_Playtime_Revise\\\":\\\"Voc\",\n    \" jogou por mais %1$s\\\",\\\"WriteReview_Dialog_RecommendGame\\\":\\\"Voc\",\n    \" recomendaria este jogo para outros jogadores?\\\",\\\"WriteReview_Dialog_RecommendGame_Software\\\":\\\"Voc\",\n    \" recomendaria este software para outros jogadores?\\\",\\\"WriteReview_Dialog_RecommendGame_Revise\\\":\\\"Deseja revisar a sua an\",\n    \"lise?\\\",\\\"WriteReview_Dialog_GetHelp_Btn\\\":\\\"Obter ajuda com a compra\\\",\\\"WriteReview_Dialog_Visibility\\\":\\\"Visibilidade:\\\",\\\"WriteReview_Dialog_Public\\\":\\\"P\",\n    \"blica\\\",\\\"WriteReview_Dialog_Friends\\\":\\\"S\",\n    \" amigos\\\",\\\"WriteReview_Dialog_Yes\\\":\\\"Sim\\\",\\\"WriteReview_Dialog_No\\\":\\\"N\",\n    \"o\\\",\\\"WriteReview_Dialog_GetSupport_Btn\\\":\\\"Obter ajuda com a compra\\\",\\\"WriteReview_Dialog_GetSupport_Desc\\\":\\\"Obtenha ajuda t\",\n    \"cnica, suporte ao cliente ou solicite um reembolso.\\\",\\\"WriteReview_Dialog_AddReview_Btn\\\":\\\"Publicar an\",\n    \"lise\\\",\\\"WriteReview_Dialog_AddReview_Desc\\\":\\\"Compartilhe a sua opini\",\n    \"o com outros jogadores.\\\",\\\"WriteReview_Dialog_AddReview_Header\\\":\\\"Deseja publicar uma an\",\n    \"lise?\\\",\\\"WriteReview_Dialog_ReviewInstructions_Link\\\":\\\"regras e diretrizes\\\",\\\"WriteReview_Dialog_ReviewInstructions\\\":\\\"Descreva o que gostou e o que n\",\n    \"o gostou neste produto e se voc\",\n    \" o recomenda a outros. N\",\n    \"o se esque\",\n    \"a de ter educa\",\n    \"o e seguir as %1$s. \",\n    \" necess\",\n    \"rio informar uma descri\",\n    \"o para publicar a sua recomenda\",\n    \"o.\\\",\\\"WriteReview_Dialog_SteamChinaDisclaimer\\\":\\\"Ao publicar esta an\",\n    \"lise, voc\",\n    \" aceita que a localiza\",\n    \"o em que a escreveu seja compartilhada com outros usu\",\n    \"rios no Steam China.\\\",\\\"WriteReview_Dialog_AllowComments\\\":\\\"Permitir coment\",\n    \"rios\\\",\\\"WriteReview_Dialog_FreeDisclaimer\\\":\\\"Assinale esta caixa caso tenha recebido o produto de gra\",\n    \"a\\\",\\\"WriteReview_Dialog_FreeDisclaimer_Tooltip\\\":\\\"Assinale esta caixa caso tenha recebido o produto de gra\",\n    \"a; o texto \\\\\\\\\\\"Produto recebido de gra\",\n    \"a\\\\\\\\\\\" ser\",\n    \" exibido junto \",\n    \"lise. Caso tenha sido remunerado(a) para escrever a an\",\n    \"lise, deixe isso claro no texto.\\\",\\\"WriteReview_Dialog_FormattingHelp\\\":\\\"Ajuda de formata\",\n    \"o\\\",\\\"WriteReview_Dialog_GenericError\\\":\\\"Ocorreu um erro ao publicar a sua an\",\n    \"lise. Tente novamente mais tarde.\\\",\\\"WriteReview_Dialog_NoTextError\\\":\\\"Descreva o que gostou ou n\",\n    \"o neste produto.\\\",\\\"WriteReview_Dialog_Delay\\\":\\\"Talvez depois\\\",\\\"Broadcast_View_Stack_H\\\":\\\"Exibi\",\n    \"o horizontal\\\",\\\"Broadcast_View_Stack_V\\\":\\\"Exibi\",\n    \"o vertical\\\",\\\"Broadcast_View_Theater\\\":\\\"Modo cinema\\\",\\\"Broadcast_View_Fullscreen\\\":\\\"Tela cheia\\\",\\\"Broadcast_View_HideChat\\\":\\\"Ocultar conversa\\\",\\\"Broadcast_View_ShowBothChats\\\":\\\"Exibir as duas conversas\\\",\\\"Broadcast_View_ShowSingleChats\\\":\\\"Exibir s\",\n    \" uma conversa\\\",\\\"Broadcast_View_ShowChat\\\":\\\"Exibir conversa\\\",\\\"Broadcast_Store_FreeToPlay\\\":\\\"Gratuito para jogar\\\",\\\"Broadcast_PartnerChat_Login\\\":\\\"Inicie a sess\",\n    \"o com a sua conta de parceiro Steamworks para conversar\\\",\\\"PartnerEvent_1\\\":\\\"Outro evento\\\",\\\"PartnerEvent_2\\\":\\\"Evento de jogo\\\",\\\"PartnerEvent_3\\\":\\\"Evento de grupos\\\",\\\"PartnerEvent_4\\\":\\\"Encontro\\\",\\\"PartnerEvent_5\\\":\\\"Causa especial\\\",\\\"PartnerEvent_6\\\":\\\"Evento de m\",\n    \"sica e artes\\\",\\\"PartnerEvent_7\\\":\\\"Evento esportivo\\\",\\\"PartnerEvent_8\\\":\\\"Evento de viagem ao vivo\\\",\\\"PartnerEvent_9\\\":\\\"Conversa\\\",\\\"PartnerEvent_9_editor\\\":\\\"Conversa / Sess\",\n    \"o de perguntas e respostas\\\",\\\"PartnerEvent_10\\\":\\\"Lan\",\n    \"amento de jogo\\\",\\\"PartnerEvent_10_editor\\\":\\\"O jogo j\",\n    \" est\",\n    \" dispon\",\n    \"vel!\\\",\\\"PartnerEvent_11\\\":\\\"Transmiss\",\n    \"o ao vivo\\\",\\\"PartnerEvent_12\\\":\\\"Pequena atualiza\",\n    \"o\\\",\\\"PartnerEvent_12_editor\\\":\\\"Pequena atualiza\",\n    \"o\\\",\\\"PartnerEvent_13\\\":\\\"Atualiza\",\n    \"o\\\",\\\"PartnerEvent_14\\\":\\\"Grande atualiza\",\n    \"o\\\",\\\"PartnerEvent_15\\\":\\\"Lan\",\n    \"amento de conte\",\n    \"do adicional\\\",\\\"PartnerEvent_16\\\":\\\"Lan\",\n    \"amento futuro\\\",\\\"PartnerEvent_16_editor\\\":\\\"Lan\",\n    \"amento em data espec\",\n    \"fica\\\",\\\"PartnerEvent_17\\\":\\\"Transmiss\",\n    \"o de torneio\\\",\\\"PartnerEvent_18\\\":\\\"Transmiss\",\n    \"o dos desenvolvedores\\\",\\\"PartnerEvent_19\\\":\\\"Transmiss\",\n    \"o de celebridade\\\",\\\"PartnerEvent_20\\\":\\\"Jogo com desconto\\\",\\\"PartnerEvent_20_editor\\\":\\\"Desconto neste jogo\\\",\\\"PartnerEvent_21\\\":\\\"Item ou conte\",\n    \"do adicional com desconto\\\",\\\"PartnerEvent_21_editor\\\":\\\"Desconto em itens do jogo ou conte\",\n    \"do adicional\\\",\\\"PartnerEvent_22\\\":\\\"Experi\",\n    \"ncia adicional\\\",\\\"PartnerEvent_23\\\":\\\"Evento de itens\\\",\\\"PartnerEvent_24\\\":\\\"Evento de benef\",\n    \"cios\\\",\\\"PartnerEvent_25\\\":\\\"Evento de desafios\\\",\\\"PartnerEvent_26\\\":\\\"Concurso\\\",\\\"PartnerEvent_27\\\":\\\"Evento no mundo real\\\",\\\"PartnerEvent_27_editor\\\":\\\"Encontro em exposi\",\n    \"o, evento ou conven\",\n    \"o\\\",\\\"PartnerEvent_28\\\":\\\"Not\",\n    \"cias\\\",\\\"PartnerEvent_28_editor\\\":\\\"An\",\n    \"ncio / Not\",\n    \"cias\\\",\\\"PartnerEvent_29\\\":\\\"Lan\",\n    \"amento de beta\\\",\\\"PartnerEvent_29_editor\\\":\\\"Convite / Novidades do beta\\\",\\\"PartnerEvent_30\\\":\\\"Atualiza\",\n    \"o de jogo\\\",\\\"PartnerEvent_30_editor\\\":\\\"Atualiza\",\n    \"o de conte\",\n    \"do no jogo\\\",\\\"PartnerEvent_31\\\":\\\"Teste gratuito\\\",\\\"PartnerEvent_32\\\":\\\"Temporada/Passe de batalha\\\",\\\"PartnerEvent_32_editor\\\":\\\"Lan\",\n    \"amento de temporada ou passe de batalha\\\",\\\"PartnerEvent_33\\\":\\\"Atualiza\",\n    \"o de temporada\\\",\\\"PartnerEvent_34\\\":\\\"Promo\",\n    \"o cruzada\\\",\\\"PartnerEvent_35\\\":\\\"Evento no jogo\\\",\\\"PartnerEvent_35_editor\\\":\\\"Evento no jogo\\\",\\\"PartnerEvent_Other\\\":\\\"Evento de outro tipo\\\",\\\"PartnerEvent_SteamAwardNominations\\\":\\\"Solicita\",\n    \"o de indica\",\n    \"o aos Pr\",\n    \"mios Steam\\\",\\\"PartnerEvent_SteamAwardVoteRequest\\\":\\\"Pedido de voto para os Pr\",\n    \"mios Steam\\\",\\\"PartnerEvent_SteamGameFestival_ArtistState\\\":\\\"Steam Vem A\",\n    \": declara\",\n    \"o do artista\\\",\\\"PartnerEvent_SteamGameFestival_Broadcast\\\":\\\"Steam Vem A\",\n    \": transmiss\",\n    \"o ao vivo\\\",\\\"PartnerEvent_SteamGameFestival_OfficeHour\\\":\\\"Steam Vem A\",\n    \": hor\",\n    \"rio de atendimento\\\",\\\"PartnerEvent_Curator_Group_Members\\\":\\\"An\",\n    \"ncio de grupo de curador\\\",\\\"PartnerEvent_Curator_Public\\\":\\\"Not\",\n    \"cia p\",\n    \"blica de curador\\\",\\\"ClanMembershipList\\\":\\\"Ver lista de membros\\\",\\\"MobileLogin_NoSteamAccount\\\":\\\"N\",\n    \"o tem uma conta Steam?\\\",\\\"MobileLogin_CreateAccount\\\":\\\"Cadastrar-se\\\",\\\"MobileLogin_ForgotPassword\\\":\\\"Esqueceu o seu nome de usu\",\n    \"rio ou senha?\\\",\\\"MobileLogin_RefreshCaptcha\\\":\\\"Atualizar\\\",\\\"MobileLogin_SignIn\\\":\\\"Iniciar sess\",\n    \"o\\\",\\\"MobileLogin_SigningIn\\\":\\\"Iniciando a sess\",\n    \"o\\\",\\\"MobileLogin_AccountName\\\":\\\"Nome de usu\",\n    \"rio Steam\\\",\\\"MobileLogin_Password\\\":\\\"Senha\\\",\\\"MobileLogin_CaptchaVerification\\\":\\\"Verifica\",\n    \"o\\\",\\\"MobileLogin_Enter2FA\\\":\\\"Informe o c\",\n    \"digo gerado na aba do Steam Guard no seu aplicativo m\",\n    \"vel do Steam.\\\",\\\"MobileLogin_Enter2FAHelp\\\":\\\"N\",\n    \"o tenho acesso ao meu c\",\n    \"digo do Steam Guard\\\",\\\"MobileLogin_Enter2FAShort\\\":\\\"Insira o c\",\n    \"digo do seu autenticador m\",\n    \"vel do Steam\\\",\\\"MobileLogin_EnterSteamguard\\\":\\\"N\",\n    \"o recebi o e-mail do c\",\n    \"digo do Steam Guard\\\",\\\"MobileLogin_SteamguardCode\\\":\\\"C\",\n    \"digo do Steam Guard\\\",\\\"MobileLogin_SteamguardSubmit\\\":\\\"Enviar e iniciar a sess\",\n    \"o\\\",\\\"MobileLogin_SentSteamguard_1\\\":\\\"Enviamos uma mensagem para o seu\\\",\\\"MobileLogin_SentSteamguard_2\\\":\\\"e-mail. Informe o c\",\n    \"digo fornecido pelo Steam Guard.\\\",\\\"MobileLogin_IncorrectSteamGuard\\\":\\\"O c\",\n    \"digo do Steam Guard informado est\",\n    \" incorreto. Confirme o c\",\n    \"digo e tente novamente.\\\",\\\"MobileLogin_NeedSignInHelp\\\":\\\"Preciso de ajuda para iniciar a sess\",\n    \"o\\\",\\\"MobileLogin_FreeAndEasy\\\":\\\"\",\n    \" gratuito e f\",\n    \"cil. Descubra milhares de jogos de computador para jogar com milh\",\n    \"es de novos amigos.\\\",\\\"MobileLogin_LearnMoreAboutSteam\\\":\\\"Saiba mais sobre o Steam\\\",\\\"MobileLogin_Error_RateLimitExceeded\\\":\\\"Houve muitas tentativas fracassadas de in\",\n    \"cio de sess\",\n    \"o a partir da sua rede em um curto per\",\n    \"odo de tempo. Aguarde e tente novamente mais tarde.\\\",\\\"Login_SignInTitle\\\":\\\"Iniciar sess\",\n    \"o\\\",\\\"Login_SignIn\\\":\\\"Iniciar sess\",\n    \"o\\\",\\\"Login_SigningIn\\\":\\\"Iniciando a sess\",\n    \"o\\\",\\\"Login_AccountName\\\":\\\"Nome de usu\",\n    \"rio Steam\\\",\\\"Login_Password\\\":\\\"Senha\\\",\\\"Login_RememberMe\\\":\\\"Lembrar de mim neste computador\\\",\\\"Login_RememberMe_Short\\\":\\\"Lembre-me\\\",\\\"Login_RememberMe_Tooltip\\\":\\\"Da pr\",\n    \"xima vez que iniciar o Steam, voc\",\n    \"o precisar\",\n    \" informar a sua senha ou confirmar o in\",\n    \"cio de sess\",\n    \"o.\\\",\\\"Login_InsecureComputer\\\":\\\"Pelas configura\",\n    \"es do Steam, as credenciais das contas n\",\n    \"o armazenadas neste computador.\\\",\\\"Login_ForgotPassword\\\":\\\"Esqueceu o seu nome de usu\",\n    \"rio ou senha?\\\",\\\"Login_NoSteamworksAccount\\\":\\\"Primeira vez no Steamworks?\\\",\\\"Login_CreateSteamworksAccount\\\":\\\"Saiba mais\\\",\\\"Login_NoSteamAccount\\\":\\\"N\",\n    \"o tem uma conta Steam?\\\",\\\"Login_CreateAccount\\\":\\\"Cadastre-se gratuitamente\\\",\\\"Login_CaptchaVerification\\\":\\\"Confirme que voc\",\n    \" um humano redigitando os caracteres da imagem.\\\",\\\"Login_RefreshCaptcha\\\":\\\"Atualizar\\\",\\\"Login_Enter2FA\\\":\\\"Informe o c\",\n    \"digo gerado na aba do Steam Guard no seu aplicativo m\",\n    \"vel do Steam.\\\",\\\"Login_Enter2FAHelp\\\":\\\"N\",\n    \"o tenho acesso ao meu c\",\n    \"digo do Steam Guard\\\",\\\"Login_EnterSteamguard\\\":\\\"N\",\n    \"o recebi um e-mail do Steam Guard\\\",\\\"Login_SteamguardSubmit\\\":\\\"Enviar e iniciar a sess\",\n    \"o\\\",\\\"Login_SentSteamguard\\\":\\\"Enviamos uma mensagem para o seu e-mail @%1$s. Informe o c\",\n    \"digo do Steam Guard fornecido.\\\",\\\"Login_SignOut\\\":\\\"Finalizar sess\",\n    \"o\\\",\\\"Login_RefreshSignIn\\\":\\\"Atualizar sess\",\n    \"o\\\",\\\"Login_ExitSteam\\\":\\\"Sair do Steam\\\",\\\"Login_RefreshReason_LoggedInElsewhere\\\":\\\"Uma sess\",\n    \"o foi iniciada com esta conta Steam em outro computador\\\",\\\"Login_RefreshReason_LogonSessionReplaced\\\":\\\"Esta conta est\",\n    \" com uma sess\",\n    \"o aberta em outro local\\\",\\\"Login_RefreshReason_InvalidPassword\\\":\\\"As credenciais da sua conta foram alteradas\\\",\\\"Login_RefreshReason_Revoked\\\":\\\"A sua sess\",\n    \"o foi encerrada\\\",\\\"Login_RefreshReason_Expired\\\":\\\"A sua sess\",\n    \"o expirou\\\",\\\"Login_RefreshReason_PasswordRequiredToKickSession\\\":\\\"Confirme as suas credenciais para finalizar a sess\"\n  ],\n  \"hex_dump\": null,\n  \"binary_info\": null,\n  \"signatures\": null,\n  \"symbols\": null,\n  \"control_flow\": null,\n  \"vulnerabilities\": null,\n  \"code_quality\": null,\n  \"dependencies\": null,\n  \"entropy\": null,\n  \"disassembly\": null,\n  \"threats\": {\n    \"matches\": [\n      {\n        \"rule_identifier\": \"network_communication\",\n        \"tags\": [\n          \"network\"\n        ],\n        \"metadata\": {\n          \"description\": \"Detects network communication patterns\",\n          \"category\": \"network\"\n        }\n      }\n    ],\n    \"threat_level\": \"Clean\",\n    \"classifications\": [],\n    \"indicators\": [\n      {\n        \"indicator_type\": \"NetworkIndicator\",\n        \"description\": \"Detects network communication patterns\",\n        \"severity\": \"Medium\",\n        \"confidence\": 0.8\n      }\n    ],\n    \"scan_stats\": {\n      \"scan_duration\": {\n        \"secs\": 0,\n        \"nanos\": 12919124\n      },\n      \"rules_evaluated\": 10,\n      \"patterns_matched\": 1,\n      \"file_size_scanned\": 241236\n    },\n    \"recommendations\": [\n      \"No significant threats detected.\",\n      \"Standard security practices recommended.\"\n    ]\n  },\n  \"behavioral\": null,\n  \"yara_indicators\": null\n}"}]}}
